Workbook
Name Acuáticas: Catálogo!$B$111:$B$126
Name Mercury: Catálogo!$B$65:$B$90
Name Parsun: Catálogo!$B$91:$B$110
Name Suzuki: Catálogo!$B$5:$B$36
Name Yamaha: Catálogo!$B$37:$B$64

Sheet Inicio
B2: Bujías NGK para fuera de borda y motos acuáticas — Colombia
B3: Catálogo de consulta, cotizador y plan comercial · Suzuki · Yamaha · Mercury · Parsun · Motos acuáticas · Elaborado el 12/10/2026
B5: Cómo está organizado el libro
B6: Pestaña | C6: Para qué sirve | D6: Quién la usa
B7: Informe | C7: Resumen comercial: cobertura por marca, las referencias que más motores atienden y hallazgos para vender. | D7: Gerencia y ventas
B8: Plan de ventas | C8: Diez acciones para vender más bujías, proyección simple de ventas y plan de 90 días. | D8: Ventas
B9: Consulta | C9: Elige marca y modelo y obtén bujía NGK, gap, torque y cantidad. También busca por bujía y ve qué motores la usan. | D9: Mostrador y talleres
B10: Catálogo | C10: Base completa con filtros: fuente, mercado y nivel de confianza de cada dato. | D10: Consulta y actualización
B11: Cotizador | C11: Cotización por motor con bujías por motor, precio de lista, descuento por tipo de cliente e IVA. | D11: Vendedor
B12: Precios y Stock | C12: Una fila por bujía: prioridad, costo, precio de lista y cuánto reponer. | D12: Compras
B13: Seguimiento | C13: Registro de clientes con fecha de próxima reposición y estado de recompra. | D13: Vendedor
B14: Parámetros | C14: Margen, IVA, descuentos, umbrales de prioridad y stock mínimo (supuestos editables). | D14: Gerencia
B16: Leyenda
B17: Celda amarilla | C17: Se escribe o se elige de la lista (letra azul).
B18: Celda sin color | C18: Fórmula: no se escribe encima.
B19: Confirmado | C19: Dato tomado de un manual, una ficha técnica o un catálogo oficial.
B20: Por equivalencia | C20: Motor idéntico a otro con dato oficial, pero sin manual propio: confirma con la bujía instalada.
B21: Verificar | C21: Depende del año o la serie, o no hay fuente: confirma siempre con la bujía instalada.
B23: Protocolo de atención en 6 pasos
B24: Paso 1 | C24: Pide marca, modelo exacto, año y número de serie (mejor, foto de la placa del motor).
B25: Paso 2 | C25: Búscalo en Consulta. Si el dato sale ámbar o rojo, pide ver la bujía instalada antes de despachar.
B26: Paso 3 | C26: Confirma si es 2T o 4T, cuántas bujías lleva y si requiere resistor (EFI, CDI electrónico, instrumentos).
B27: Paso 4 | C27: Cotiza el juego completo en el Cotizador, no una bujía suelta.
B28: Paso 5 | C28: Ofrece los complementos del servicio: filtro de combustible, aceite de caja, impulsor de bomba de agua y ánodos.
B29: Paso 6 | C29: Registra al cliente en Seguimiento con la fecha de venta para avisarle del siguiente cambio.
B31: Fuentes
B32: • Suzuki Marine Colombia: suzuki.com.co (catálogo de motores en venta).
B33: • Yamaha: fichas técnicas de Eduardoño (eduardono.com), distribuidor en Colombia.
B34: • Mercury Marine Latinoamérica: mercurymarine.com/lam/es y tabla oficial de bujías 2022.
B35: • Parsun: manuales y repuestos en parsun.eu; modelos en venta según Surtiminas (surtiminas.com/categoria-producto/nautica).
B36: • NGK: buscador de bujías (ngkntk.com) y catálogos; distribuidor NZ (Smart Marine) para bujías Parsun 2T.
B38: Aviso: los datos consolidan fuentes públicas a octubre de 2026. Verifica siempre con la bujía instalada o el manual del motor, sobre todo en filas marcadas Por equivalencia o Verificar. Los precios, márgenes y descuentos del libro son supuestos de ejemplo.

Sheet Informe
B1: Informe comercial: bujías NGK para fuera de borda y motos acuáticas en Colombia
B2: Suzuki · Yamaha · Mercury · Parsun · Motos acuáticas | Elaborado el 12/10/2026 | Cifras calculadas con fórmulas desde la pestaña Catálogo
B4: Modelos catalogados | D4: Referencias NGK distintas | F4: Modelos en venta actual | H4: Datos confirmados
B5: =COUNTA(Catálogo!$B$5:$B$126) -> 122 | D5: =COUNTA('Precios y Stock'!$A$5:$A$56) -> 52 | F5: =COUNTIF(Catálogo!$I$5:$I$126,"Venta actual") -> 49 | H5: =COUNTIF(Catálogo!$J$5:$J$126,"Confirmado")/COUNTA(Catálogo!$B$5:$B$126) -> 0.75409836
B6: de las 5 familias de motor | D6: bujías únicas a comprar | F6: catálogos vigentes en Colombia | H6: con manual, ficha o catálogo oficial
B8: Cobertura por marca
B9: Marca | C9: Modelos | D9: 4 tiempos | E9: 2 tiempos | F9: Venta actual | G9: Datos confirmados | H9: Bujías distintas
B10: Suzuki | C10: =COUNTIF(Catálogo!$A$5:$A$126,B10) -> 32 | D10: =COUNTIFS(Catálogo!$A$5:$A$126,B10,Catálogo!$C$5:$C$126,"4T") -> 23 | E10: =COUNTIFS(Catálogo!$A$5:$A$126,B10,Catálogo!$C$5:$C$126,"2T") -> 9 | F10: =COUNTIFS(Catálogo!$A$5:$A$126,B10,Catálogo!$I$5:$I$126,"Venta actual") -> 12 | G10: =COUNTIFS(Catálogo!$A$5:$A$126,B10,Catálogo!$J$5:$J$126,"Confirmado")/C10 -> 1 | H10: =SUMPRODUCT((Catálogo!$A$5:$A$126=B10)/COUNTIFS(Catálogo!$A$5:$A$126,Catálogo!$A$5:$A$126,Catálogo!$E$5:$E$126,Catálogo!$E$5:$E$126)) -> 15
B11: Yamaha | C11: =COUNTIF(Catálogo!$A$5:$A$126,B11) -> 28 | D11: =COUNTIFS(Catálogo!$A$5:$A$126,B11,Catálogo!$C$5:$C$126,"4T") -> 19 | E11: =COUNTIFS(Catálogo!$A$5:$A$126,B11,Catálogo!$C$5:$C$126,"2T") -> 9 | F11: =COUNTIFS(Catálogo!$A$5:$A$126,B11,Catálogo!$I$5:$I$126,"Venta actual") -> 17 | G11: =COUNTIFS(Catálogo!$A$5:$A$126,B11,Catálogo!$J$5:$J$126,"Confirmado")/C11 -> 0.60714286 | H11: =SUMPRODUCT((Catálogo!$A$5:$A$126=B11)/COUNTIFS(Catálogo!$A$5:$A$126,Catálogo!$A$5:$A$126,Catálogo!$E$5:$E$126,Catálogo!$E$5:$E$126)) -> 12
B12: Mercury | C12: =COUNTIF(Catálogo!$A$5:$A$126,B12) -> 26 | D12: =COUNTIFS(Catálogo!$A$5:$A$126,B12,Catálogo!$C$5:$C$126,"4T") -> 14 | E12: =COUNTIFS(Catálogo!$A$5:$A$126,B12,Catálogo!$C$5:$C$126,"2T") -> 12 | F12: =COUNTIFS(Catálogo!$A$5:$A$126,B12,Catálogo!$I$5:$I$126,"Venta actual") -> 0 | G12: =COUNTIFS(Catálogo!$A$5:$A$126,B12,Catálogo!$J$5:$J$126,"Confirmado")/C12 -> 0.96153846 | H12: =SUMPRODUCT((Catálogo!$A$5:$A$126=B12)/COUNTIFS(Catálogo!$A$5:$A$126,Catálogo!$A$5:$A$126,Catálogo!$E$5:$E$126,Catálogo!$E$5:$E$126)) -> 18
B13: Parsun | C13: =COUNTIF(Catálogo!$A$5:$A$126,B13) -> 20 | D13: =COUNTIFS(Catálogo!$A$5:$A$126,B13,Catálogo!$C$5:$C$126,"4T") -> 12 | E13: =COUNTIFS(Catálogo!$A$5:$A$126,B13,Catálogo!$C$5:$C$126,"2T") -> 8 | F13: =COUNTIFS(Catálogo!$A$5:$A$126,B13,Catálogo!$I$5:$I$126,"Venta actual") -> 15 | G13: =COUNTIFS(Catálogo!$A$5:$A$126,B13,Catálogo!$J$5:$J$126,"Confirmado")/C13 -> 0.7 | H13: =SUMPRODUCT((Catálogo!$A$5:$A$126=B13)/COUNTIFS(Catálogo!$A$5:$A$126,Catálogo!$A$5:$A$126,Catálogo!$E$5:$E$126,Catálogo!$E$5:$E$126)) -> 9
B14: Acuáticas | C14: =COUNTIF(Catálogo!$A$5:$A$126,B14) -> 16 | D14: =COUNTIFS(Catálogo!$A$5:$A$126,B14,Catálogo!$C$5:$C$126,"4T") -> 12 | E14: =COUNTIFS(Catálogo!$A$5:$A$126,B14,Catálogo!$C$5:$C$126,"2T") -> 4 | F14: =COUNTIFS(Catálogo!$A$5:$A$126,B14,Catálogo!$I$5:$I$126,"Venta actual") -> 5 | G14: =COUNTIFS(Catálogo!$A$5:$A$126,B14,Catálogo!$J$5:$J$126,"Confirmado")/C14 -> 0.25 | H14: =SUMPRODUCT((Catálogo!$A$5:$A$126=B14)/COUNTIFS(Catálogo!$A$5:$A$126,Catálogo!$A$5:$A$126,Catálogo!$E$5:$E$126,Catálogo!$E$5:$E$126)) -> 10
B15: Total | C15: =SUM(C10:C14) -> 122 | D15: =SUM(D10:D14) -> 80 | E15: =SUM(E10:E14) -> 42 | F15: =SUM(F10:F14) -> 49 | G15: =COUNTIF(Catálogo!$J$5:$J$126,"Confirmado")/C15 -> 0.75409836 | H15: =COUNTA('Precios y Stock'!$A$5:$A$56) -> 52
B16: La suma de 'Bujías distintas' por marca supera el total porque una misma bujía sirve a varias marcas. Mercury muestra 0 en venta actual porque su tabla oficial mezcla series antiguas y actuales: verifica siempre el año. En Acuáticas, la venta actual corresponde a Sea-Doo (distribuidor oficial en Colombia); Yamaha y Kawasaki quedan por verificar.
B17: Las 10 referencias que más motores cubren (prioridad de inventario)
B18: Bujía NGK | C18: Modelos que la usan | D18: Suzuki | E18: Yamaha | F18: Mercury | G18: Parsun | H18: Acuáticas | I18: Prioridad | J18: % del catálogo
B19: =INDEX('Precios y Stock'!$A$5:$A$56,MATCH(1,'Precios y Stock'!$L$5:$L$56,0)) -> DCPR6E | C19: =INDEX('Precios y Stock'!$C$5:$C$56,MATCH(1,'Precios y Stock'!$L$5:$L$56,0)) -> 8 | D19: =COUNTIFS(Catálogo!$E$5:$E$126,$B19,Catálogo!$A$5:$A$126,"Suzuki") -> 5 | E19: =COUNTIFS(Catálogo!$E$5:$E$126,$B19,Catálogo!$A$5:$A$126,"Yamaha") -> 0 | F19: =COUNTIFS(Catálogo!$E$5:$E$126,$B19,Catálogo!$A$5:$A$126,"Mercury") -> 3 | G19: =COUNTIFS(Catálogo!$E$5:$E$126,$B19,Catálogo!$A$5:$A$126,"Parsun") -> 0 | H19: =COUNTIFS(Catálogo!$E$5:$E$126,$B19,Catálogo!$A$5:$A$126,"Acuáticas") -> 0 | I19: =INDEX('Precios y Stock'!$E$5:$E$56,MATCH(1,'Precios y Stock'!$L$5:$L$56,0)) -> Alta | J19: =C19/$C$15 -> 0.06557377
B20: =INDEX('Precios y Stock'!$A$5:$A$56,MATCH(2,'Precios y Stock'!$L$5:$L$56,0)) -> LFR6A-11 | C20: =INDEX('Precios y Stock'!$C$5:$C$56,MATCH(2,'Precios y Stock'!$L$5:$L$56,0)) -> 8 | D20: =COUNTIFS(Catálogo!$E$5:$E$126,$B20,Catálogo!$A$5:$A$126,"Suzuki") -> 0 | E20: =COUNTIFS(Catálogo!$E$5:$E$126,$B20,Catálogo!$A$5:$A$126,"Yamaha") -> 7 | F20: =COUNTIFS(Catálogo!$E$5:$E$126,$B20,Catálogo!$A$5:$A$126,"Mercury") -> 1 | G20: =COUNTIFS(Catálogo!$E$5:$E$126,$B20,Catálogo!$A$5:$A$126,"Parsun") -> 0 | H20: =COUNTIFS(Catálogo!$E$5:$E$126,$B20,Catálogo!$A$5:$A$126,"Acuáticas") -> 0 | I20: =INDEX('Precios y Stock'!$E$5:$E$56,MATCH(2,'Precios y Stock'!$L$5:$L$56,0)) -> Alta | J20: =C20/$C$15 -> 0.06557377
B21: =INDEX('Precios y Stock'!$A$5:$A$56,MATCH(3,'Precios y Stock'!$L$5:$L$56,0)) -> BKR6E | C21: =INDEX('Precios y Stock'!$C$5:$C$56,MATCH(3,'Precios y Stock'!$L$5:$L$56,0)) -> 6 | D21: =COUNTIFS(Catálogo!$E$5:$E$126,$B21,Catálogo!$A$5:$A$126,"Suzuki") -> 6 | E21: =COUNTIFS(Catálogo!$E$5:$E$126,$B21,Catálogo!$A$5:$A$126,"Yamaha") -> 0 | F21: =COUNTIFS(Catálogo!$E$5:$E$126,$B21,Catálogo!$A$5:$A$126,"Mercury") -> 0 | G21: =COUNTIFS(Catálogo!$E$5:$E$126,$B21,Catálogo!$A$5:$A$126,"Parsun") -> 0 | H21: =COUNTIFS(Catálogo!$E$5:$E$126,$B21,Catálogo!$A$5:$A$126,"Acuáticas") -> 0 | I21: =INDEX('Precios y Stock'!$E$5:$E$56,MATCH(3,'Precios y Stock'!$L$5:$L$56,0)) -> Alta | J21: =C21/$C$15 -> 0.049180328
B22: =INDEX('Precios y Stock'!$A$5:$A$56,MATCH(4,'Precios y Stock'!$L$5:$L$56,0)) -> DPR7EA-9 | C22: =INDEX('Precios y Stock'!$C$5:$C$56,MATCH(4,'Precios y Stock'!$L$5:$L$56,0)) -> 6 | D22: =COUNTIFS(Catálogo!$E$5:$E$126,$B22,Catálogo!$A$5:$A$126,"Suzuki") -> 0 | E22: =COUNTIFS(Catálogo!$E$5:$E$126,$B22,Catálogo!$A$5:$A$126,"Yamaha") -> 0 | F22: =COUNTIFS(Catálogo!$E$5:$E$126,$B22,Catálogo!$A$5:$A$126,"Mercury") -> 0 | G22: =COUNTIFS(Catálogo!$E$5:$E$126,$B22,Catálogo!$A$5:$A$126,"Parsun") -> 6 | H22: =COUNTIFS(Catálogo!$E$5:$E$126,$B22,Catálogo!$A$5:$A$126,"Acuáticas") -> 0 | I22: =INDEX('Precios y Stock'!$E$5:$E$56,MATCH(4,'Precios y Stock'!$L$5:$L$56,0)) -> Alta | J22: =C22/$C$15 -> 0.049180328
B23: =INDEX('Precios y Stock'!$A$5:$A$56,MATCH(5,'Precios y Stock'!$L$5:$L$56,0)) -> BPR7HS | C23: =INDEX('Precios y Stock'!$C$5:$C$56,MATCH(5,'Precios y Stock'!$L$5:$L$56,0)) -> 5 | D23: =COUNTIFS(Catálogo!$E$5:$E$126,$B23,Catálogo!$A$5:$A$126,"Suzuki") -> 0 | E23: =COUNTIFS(Catálogo!$E$5:$E$126,$B23,Catálogo!$A$5:$A$126,"Yamaha") -> 0 | F23: =COUNTIFS(Catálogo!$E$5:$E$126,$B23,Catálogo!$A$5:$A$126,"Mercury") -> 0 | G23: =COUNTIFS(Catálogo!$E$5:$E$126,$B23,Catálogo!$A$5:$A$126,"Parsun") -> 5 | H23: =COUNTIFS(Catálogo!$E$5:$E$126,$B23,Catálogo!$A$5:$A$126,"Acuáticas") -> 0 | I23: =INDEX('Precios y Stock'!$E$5:$E$56,MATCH(5,'Precios y Stock'!$L$5:$L$56,0)) -> Alta | J23: =C23/$C$15 -> 0.040983607
B24: =INDEX('Precios y Stock'!$A$5:$A$56,MATCH(6,'Precios y Stock'!$L$5:$L$56,0)) -> LFR5A-11 | C24: =INDEX('Precios y Stock'!$C$5:$C$56,MATCH(6,'Precios y Stock'!$L$5:$L$56,0)) -> 5 | D24: =COUNTIFS(Catálogo!$E$5:$E$126,$B24,Catálogo!$A$5:$A$126,"Suzuki") -> 0 | E24: =COUNTIFS(Catálogo!$E$5:$E$126,$B24,Catálogo!$A$5:$A$126,"Yamaha") -> 3 | F24: =COUNTIFS(Catálogo!$E$5:$E$126,$B24,Catálogo!$A$5:$A$126,"Mercury") -> 2 | G24: =COUNTIFS(Catálogo!$E$5:$E$126,$B24,Catálogo!$A$5:$A$126,"Parsun") -> 0 | H24: =COUNTIFS(Catálogo!$E$5:$E$126,$B24,Catálogo!$A$5:$A$126,"Acuáticas") -> 0 | I24: =INDEX('Precios y Stock'!$E$5:$E$56,MATCH(6,'Precios y Stock'!$L$5:$L$56,0)) -> Alta | J24: =C24/$C$15 -> 0.040983607
B25: =INDEX('Precios y Stock'!$A$5:$A$56,MATCH(7,'Precios y Stock'!$L$5:$L$56,0)) -> LKR6E | C25: =INDEX('Precios y Stock'!$C$5:$C$56,MATCH(7,'Precios y Stock'!$L$5:$L$56,0)) -> 5 | D25: =COUNTIFS(Catálogo!$E$5:$E$126,$B25,Catálogo!$A$5:$A$126,"Suzuki") -> 3 | E25: =COUNTIFS(Catálogo!$E$5:$E$126,$B25,Catálogo!$A$5:$A$126,"Yamaha") -> 1 | F25: =COUNTIFS(Catálogo!$E$5:$E$126,$B25,Catálogo!$A$5:$A$126,"Mercury") -> 0 | G25: =COUNTIFS(Catálogo!$E$5:$E$126,$B25,Catálogo!$A$5:$A$126,"Parsun") -> 1 | H25: =COUNTIFS(Catálogo!$E$5:$E$126,$B25,Catálogo!$A$5:$A$126,"Acuáticas") -> 0 | I25: =INDEX('Precios y Stock'!$E$5:$E$56,MATCH(7,'Precios y Stock'!$L$5:$L$56,0)) -> Alta | J25: =C25/$C$15 -> 0.040983607
B26: =INDEX('Precios y Stock'!$A$5:$A$56,MATCH(8,'Precios y Stock'!$L$5:$L$56,0)) -> BPZ8H-N-10 | C26: =INDEX('Precios y Stock'!$C$5:$C$56,MATCH(8,'Precios y Stock'!$L$5:$L$56,0)) -> 4 | D26: =COUNTIFS(Catálogo!$E$5:$E$126,$B26,Catálogo!$A$5:$A$126,"Suzuki") -> 0 | E26: =COUNTIFS(Catálogo!$E$5:$E$126,$B26,Catálogo!$A$5:$A$126,"Yamaha") -> 0 | F26: =COUNTIFS(Catálogo!$E$5:$E$126,$B26,Catálogo!$A$5:$A$126,"Mercury") -> 4 | G26: =COUNTIFS(Catálogo!$E$5:$E$126,$B26,Catálogo!$A$5:$A$126,"Parsun") -> 0 | H26: =COUNTIFS(Catálogo!$E$5:$E$126,$B26,Catálogo!$A$5:$A$126,"Acuáticas") -> 0 | I26: =INDEX('Precios y Stock'!$E$5:$E$56,MATCH(8,'Precios y Stock'!$L$5:$L$56,0)) -> Media | J26: =C26/$C$15 -> 0.032786885
B27: =INDEX('Precios y Stock'!$A$5:$A$56,MATCH(9,'Precios y Stock'!$L$5:$L$56,0)) -> BR8HS-10 | C27: =INDEX('Precios y Stock'!$C$5:$C$56,MATCH(9,'Precios y Stock'!$L$5:$L$56,0)) -> 4 | D27: =COUNTIFS(Catálogo!$E$5:$E$126,$B27,Catálogo!$A$5:$A$126,"Suzuki") -> 2 | E27: =COUNTIFS(Catálogo!$E$5:$E$126,$B27,Catálogo!$A$5:$A$126,"Yamaha") -> 1 | F27: =COUNTIFS(Catálogo!$E$5:$E$126,$B27,Catálogo!$A$5:$A$126,"Mercury") -> 0 | G27: =COUNTIFS(Catálogo!$E$5:$E$126,$B27,Catálogo!$A$5:$A$126,"Parsun") -> 1 | H27: =COUNTIFS(Catálogo!$E$5:$E$126,$B27,Catálogo!$A$5:$A$126,"Acuáticas") -> 0 | I27: =INDEX('Precios y Stock'!$E$5:$E$56,MATCH(9,'Precios y Stock'!$L$5:$L$56,0)) -> Media | J27: =C27/$C$15 -> 0.032786885
B28: =INDEX('Precios y Stock'!$A$5:$A$56,MATCH(10,'Precios y Stock'!$L$5:$L$56,0)) -> DCPR8E | C28: =INDEX('Precios y Stock'!$C$5:$C$56,MATCH(10,'Precios y Stock'!$L$5:$L$56,0)) -> 4 | D28: =COUNTIFS(Catálogo!$E$5:$E$126,$B28,Catálogo!$A$5:$A$126,"Suzuki") -> 0 | E28: =COUNTIFS(Catálogo!$E$5:$E$126,$B28,Catálogo!$A$5:$A$126,"Yamaha") -> 0 | F28: =COUNTIFS(Catálogo!$E$5:$E$126,$B28,Catálogo!$A$5:$A$126,"Mercury") -> 0 | G28: =COUNTIFS(Catálogo!$E$5:$E$126,$B28,Catálogo!$A$5:$A$126,"Parsun") -> 0 | H28: =COUNTIFS(Catálogo!$E$5:$E$126,$B28,Catálogo!$A$5:$A$126,"Acuáticas") -> 4 | I28: =INDEX('Precios y Stock'!$E$5:$E$56,MATCH(10,'Precios y Stock'!$L$5:$L$56,0)) -> Media | J28: =C28/$C$15 -> 0.032786885
B29: Total de las 10 | C29: =SUM(C19:C28) -> 55 | D29: =SUM(D19:D28) -> 16 | E29: =SUM(E19:E28) -> 12 | F29: =SUM(F19:F28) -> 10 | G29: =SUM(G19:G28) -> 13 | H29: =SUM(H19:H28) -> 4 | J29: =C29/$C$15 -> 0.45081967
B31: Hallazgos clave para vender
B32: ="1. Pocas referencias cubren gran parte del catálogo: las 10 primeras atienden el "&TEXT(J29,"0%")&" de los modelos. Tener stock de ellas primero da la mayor cobertura con la menor inversión." -> 1. Pocas referencias cubren gran parte del catálogo: las 10 primeras atienden el 45% de los modelos. Tener stock de ellas primero da la mayor cobertura con la menor inversión.
B33: 2. Una misma bujía atiende marcas distintas: LKR6E cubre Suzuki DF115/DF150, Yamaha F115B y Parsun F-115; DCPR6E sirve a varios Suzuki de 25 a 100 HP y a los FourStroke pequeños de Mercury; LFR5A-11 y LFR6A-11 sirven a Yamaha y Mercury de 75 a 300 HP.
B34: 3. Parecidas no son iguales: LKR6E (rosca 12 mm, alcance 26,5 mm) y BKR6E (rosca 14 mm, alcance 19 mm) no son intercambiables. Parsun usa DPR7EA-9, un rango más frío, donde Yamaha usa DPR6EB-9 (F-20 y F-60 frente a F20C y FT60J). Un rango térmico incorrecto produce fallas de encendido o sobrecalentamiento.
B35: 4. Revisa el resistor: los motores con inyección electrónica (EFI), CDI electrónico o instrumentos de navegación lo suelen exigir (referencias con R, como DCPR6E o BPR7HS). Excepción: algunos 2T de Yamaha usan referencias sin resistor (B7HS, B8HS-10). Manda el manual del fabricante.
B36: 5. Se vende por juego, no por unidad: 2 bujías en un bicilíndrico, 4 en un cuatro cilindros y 6 en un V6. Cotiza siempre el juego completo.
B37: 6. Confirma con la bujía instalada los datos marcados Por equivalencia o Verificar (Parsun F-115, T-2C, T-5, T-25, T-75, LT7 y los históricos de Yamaha y Mercury, que cambian según año y serie).
B38: 7. Hay discrepancias entre fuentes: Mercury 40/50/60 EFI trae Champion RA8HC de fábrica y NGK lista DCPR7E; en Parsun F8/F9.8 y F20/F25 el manual dice DPR7EA-9 y el catálogo de repuestos DPR6EA-9.
B39: 8. Motos acuáticas: Sea-Doo es la marca con distribuidor oficial en Colombia y sus motores recientes usan solo tres bujías (CR8EB en los Spark, DCPR8E en los de 130 a 230 HP y KR9E-G en los de 300 HP). Yamaha y Kawasaki quedan por verificar: confirma primero cuántas máquinas circulan en tu zona antes de comprar stock.
B41: Argumentos de venta
B42: Para el taller | F42: Para el cliente final
B43: • Un solo proveedor para fuera de borda y motos acuáticas: menos tiempo buscando la referencia. | F43: • La bujía que indica el fabricante para su motor, no 'la que parece servir'.
B44: • Respuesta en minutos con gap y torque listos para el mecánico. | F44: • Menos riesgo de fallas de encendido: una bujía equivocada o desgastada es causa común.
B45: • Juego completo por motor: sin viajes de vuelta por faltantes. | F45: • Cambio de la referencia si no corresponde (política que tú defines).
B46: • Precio escalonado por volumen y entrega rápida de las referencias de prioridad Alta. | F46: • Aviso por WhatsApp cuando se acerca el siguiente cambio.

Sheet Plan de ventas
B1: Plan de ventas: qué más ayuda a vender más bujías
B2: Recomendaciones ordenadas por impacto esperado. Son hipótesis de trabajo: mide resultados y ajusta.
B4: # | C4: Acción | D4: Por qué ayuda | E4: Cómo ejecutarla | F4: Prioridad | G4: Esfuerzo
B5: 1 | C5: Vender por kit de servicio | D5: Un V6 usa 6 bujías y un cuatro cilindros, 4: el ticket crece al vender el juego completo y los complementos del servicio. | E5: Arma kits por motor desde el Cotizador: juego de bujías + filtro de combustible + aceite de caja + impulsor de bomba de agua + ánodos. Ofrece un precio de kit con un descuento pequeño. | F5: Alta | G5: Bajo
B6: 2 | C6: Stock de las referencias de mayor cobertura | D6: Pocas referencias atienden muchos modelos (ver Informe): inventario reducido con alta disponibilidad. | E6: Compra primero las de prioridad Alta en 'Precios y Stock' y mantén el mínimo sugerido. Revisa la columna 'Reponer' cada semana. | F6: Alta | G6: Bajo
B7: 3 | C7: Programa para talleres | D7: Un taller recompra todas las semanas; un cliente final, una vez al año. | E7: Lista escalonada (Parámetros), pedido mínimo bajo, entrega en 24 horas y cuenta mensual para talleres con volumen. | F7: Alta | G7: Medio
B8: 4 | C8: Consulta por WhatsApp con foto de la placa | D8: Reduce errores de referencia y devoluciones; el taller te prefiere porque resuelves rápido. | E8: Pide foto de la placa del motor (serie y año), responde con la ficha de Consulta (bujía, gap, torque) y envía la cotización. | F8: Alta | G8: Bajo
B9: 5 | C9: Recordatorio de recompra | D9: Los cambios son periódicos: avisar a tiempo evita que el cliente compre en otro lado. | E9: Registra cada venta en Seguimiento y escribe al cliente cuando el estado pase a 'Próximos 30 días'. Ajusta el intervalo según el manual de cada motor. | F9: Alta | G9: Bajo
B10: 6 | C10: Alianzas en puntos de alto volumen | D10: Las flotas y los grupos compran por docenas de motores. | E10: Visita cooperativas de pesca, transporte fluvial, minería aluvial, marinas y operadores turísticos de tu zona; ofrece diagnóstico gratis y contrato de suministro. | F10: Media | G10: Medio
B11: 7 | C11: Campañas por temporada | D11: Semana Santa, vacaciones de mitad de año y diciembre–enero suelen concentrar el uso recreativo y turístico. | E11: Lanza la campaña 3 o 4 semanas antes, con kits listos y stock reforzado de las referencias de prioridad Alta. | F11: Media | G11: Bajo
B12: 8 | C12: Mini-capacitación a mecánicos | D12: Quien explica, vende: te posicionas como asesor y no como simple proveedor. | E12: Sesión de 20 minutos en el taller: cómo leer el estado de la bujía, rango térmico, resistor y mezcla 50:1 en los 2T Parsun. | F12: Media | G12: Medio
B13: 9 | C13: Agregar equivalencias de otras marcas de bujía | D13: Cuando el cliente trae otra marca (por ejemplo Champion), tener la equivalencia evita perder la venta. | E13: Añade columnas de equivalencia a la pestaña Catálogo. En este libro no están verificadas, por eso no se incluyeron. | F13: Media | G13: Medio
B14: 10 | C14: Completar los datos pendientes | D14: Menos riesgo de error y más confianza al cotizar. | E14: En las filas ámbar y rojas del Catálogo, anota la bujía que el taller ve instalada. Para Parsun, pide la ficha a Surtiminas: servicioalcliente@surtiminas.com.co o (604) 322-1205. | F14: Media | G14: Bajo
B16: Proyección simple de ventas mensuales
B17: Celdas amarillas = supuestos de ejemplo para que reemplaces con tus cifras reales.
C18: Talleres activos | D18: 10 | E18: Ejemplo: talleres que te compran de forma regular.
C19: Motores por taller que cambian bujías al mes | D19: 6 | E19: Ejemplo: pregúntalo en cada visita.
C20: Bujías por motor (promedio) | D20: =ROUND(AVERAGEIFS(Catálogo!$H$5:$H$126,Catálogo!$I$5:$I$126,"Venta actual"),1) -> 3.5 | E20: Promedio de los modelos en venta actual del catálogo; puedes sobrescribirlo con tu mezcla real.
C21: Precio promedio de venta por bujía (COP) | D21: 23000 | E21: Ejemplo ilustrativo: reemplázalo con tu precio real de lista.
C22: Descuento promedio a talleres | D22: =Parámetros!$B$11 -> 0.1 | E22: Viene de Parámetros.
C23: Margen bruto objetivo sobre el precio de lista | D23: =Parámetros!$B$5 -> 0.5 | E23: Viene de Parámetros.
C25: Bujías vendidas al mes | D25: =D18*D19*D20 -> 210
C26: Ingreso neto mensual (sin IVA, COP) | D26: =D25*D21*(1-D22) -> 4347000
C27: Margen bruto mensual estimado (COP) | D27: =D26-D25*D21*(1-D23) -> 1932000
C28: Ingreso neto anual (COP) | D28: =D26*12 -> 52164000
C29: Aporte de un taller adicional por mes (COP) | D29: =IF(D18=0,0,D26/D18) -> 434700
B31: Plan de 90 días
C32: Cuándo | D32: Acción | E32: Meta medible (sugerida: ajústala a tu zona)
C33: Semanas 1–2 | D33: Cargar costos reales en 'Precios y Stock' y definir margen y descuentos en Parámetros. | E33: Precio de lista para todas las referencias de prioridad Alta.
C34: Semanas 1–2 | D34: Armar los kits de servicio de los motores más comunes en tu zona. | E34: 5 kits con precio y código.
C35: Semanas 3–4 | D35: Visitar talleres y mostrar la pestaña Consulta con tres motores de ejemplo. | E35: 10 talleres visitados y al menos 3 primeras compras.
C36: Semanas 5–8 | D36: Activar WhatsApp Business con respuesta por foto de placa. | E36: Responder en menos de 30 minutos.
C37: Semanas 5–8 | D37: Registrar todas las ventas en Seguimiento. | E37: 100 % de las ventas con motor y fecha.
C38: Semanas 9–12 | D38: Primera ronda de recordatorios de recompra y campaña de temporada. | E38: Medir cuántos recordatorios terminan en recompra.

Sheet Consulta
B1: Consulta rápida de bujías
B2: Elige en las celdas amarillas. Respuesta inmediata para mostrador y talleres.
B4: 1. Buscar por motor
B5: Marca | C5: Suzuki | D5: ← elige la marca | H5: =IFERROR(MATCH(C5&"|"&C6,Catálogo!$M$5:$M$126,0),"") -> 4
B6: Modelo | C6: DF60AQHL/ATL | D6: ← la lista depende de la marca
B8: Bujía NGK | C8: =IF($H$5="","—",IF(INDEX(Catálogo!$E$5:$E$126,$H$5)="","—",INDEX(Catálogo!$E$5:$E$126,$H$5))) -> DCPR6E
B9: Gap (mm) | C9: =IF($H$5="","—",IF(INDEX(Catálogo!$F$5:$F$126,$H$5)="","—",INDEX(Catálogo!$F$5:$F$126,$H$5))) -> 0.8–0.9
B10: Torque (N·m) | C10: =IF($H$5="","—",IF(INDEX(Catálogo!$G$5:$G$126,$H$5)="","—",INDEX(Catálogo!$G$5:$G$126,$H$5))) -> 18
B11: Bujías por motor | C11: =IF($H$5="","—",IF(INDEX(Catálogo!$H$5:$H$126,$H$5)="","—",INDEX(Catálogo!$H$5:$H$126,$H$5))) -> 4
B12: Tipo | C12: =IF($H$5="","—",IF(INDEX(Catálogo!$C$5:$C$126,$H$5)="","—",INDEX(Catálogo!$C$5:$C$126,$H$5))) -> 4T
B13: Motor | C13: =IF($H$5="","—",IF(INDEX(Catálogo!$D$5:$D$126,$H$5)="","—",INDEX(Catálogo!$D$5:$D$126,$H$5))) -> 4 cil.
B14: Mercado | C14: =IF($H$5="","—",IF(INDEX(Catálogo!$I$5:$I$126,$H$5)="","—",INDEX(Catálogo!$I$5:$I$126,$H$5))) -> Venta actual
B15: Confianza del dato | C15: =IF($H$5="","—",IF(INDEX(Catálogo!$J$5:$J$126,$H$5)="","—",INDEX(Catálogo!$J$5:$J$126,$H$5))) -> Confirmado
B16: Fuente | C16: =IF($H$5="","—",IF(INDEX(Catálogo!$K$5:$K$126,$H$5)="","—",INDEX(Catálogo!$K$5:$K$126,$H$5))) -> suzuki.com.co
B17: Notas | C17: =IF($H$5="","—",IF(INDEX(Catálogo!$L$5:$L$126,$H$5)="","—",INDEX(Catálogo!$L$5:$L$126,$H$5))) -> OEM 09482-00446
B18: Otros modelos con la misma bujía | C18: =IF($H$5="","—",COUNTIF(Catálogo!$E$5:$E$126,C8)-1) -> 7
B19: Texto para enviar al cliente | C19: =IF($H$5="","Modelo no encontrado en el catálogo",IF(C5="Acuáticas",C6,C5&" "&C6)&": bujía NGK "&C8&", gap "&C9&" mm, "&C11&" bujía(s) por motor. Confirma con la bujía instalada si el dato figura como Por equivalencia o Verificar.") -> Suzuki DF60AQHL/ATL: bujía NGK DCPR6E, gap 0.8–0.9 mm, 4 bujía(s) por motor. Confirma con la bujía instalada si el dato figura como Por equivalencia o Verificar.
B21: 2. Buscar por bujía: ¿qué motores la usan?
B22: Bujía NGK | C22: LKR6E | D22: ← elige o escribe la referencia
B23: Modelos que la usan | C23: =COUNTIF(Catálogo!$E$5:$E$126,C22) -> 5
B25: # | C25: Marca y modelo | D25: Tipo y motor | E25: Confianza
B26: 1 | C26: =IFERROR(IF(INDEX(Catálogo!$A$5:$A$126,MATCH($B26,Catálogo!$N$5:$N$126,0))="Acuáticas",INDEX(Catálogo!$B$5:$B$126,MATCH($B26,Catálogo!$N$5:$N$126,0)),INDEX(Catálogo!$A$5:$A$126,MATCH($B26,Catálogo!$N$5:$N$126,0))&" "&INDEX(Catálogo!$B$5:$B$126,MATCH($B26,Catálogo!$N$5:$N$126,0))),"") -> Suzuki DF115BTL/BTX (Stealth/blanco) | D26: =IFERROR(INDEX(Catálogo!$C$5:$C$126,MATCH($B26,Catálogo!$N$5:$N$126,0))&" · "&INDEX(Catálogo!$D$5:$D$126,MATCH($B26,Catálogo!$N$5:$N$126,0)),"") -> 4T · 4 cil. | E26: =IFERROR(INDEX(Catálogo!$J$5:$J$126,MATCH($B26,Catálogo!$N$5:$N$126,0)),"") -> Confirmado
B27: 2 | C27: =IFERROR(IF(INDEX(Catálogo!$A$5:$A$126,MATCH($B27,Catálogo!$N$5:$N$126,0))="Acuáticas",INDEX(Catálogo!$B$5:$B$126,MATCH($B27,Catálogo!$N$5:$N$126,0)),INDEX(Catálogo!$A$5:$A$126,MATCH($B27,Catálogo!$N$5:$N$126,0))&" "&INDEX(Catálogo!$B$5:$B$126,MATCH($B27,Catálogo!$N$5:$N$126,0))),"") -> Suzuki DF150ATL/ATX/AZX | D27: =IFERROR(INDEX(Catálogo!$C$5:$C$126,MATCH($B27,Catálogo!$N$5:$N$126,0))&" · "&INDEX(Catálogo!$D$5:$D$126,MATCH($B27,Catálogo!$N$5:$N$126,0)),"") -> 4T · 4 cil. | E27: =IFERROR(INDEX(Catálogo!$J$5:$J$126,MATCH($B27,Catálogo!$N$5:$N$126,0)),"") -> Confirmado
B28: 3 | C28: =IFERROR(IF(INDEX(Catálogo!$A$5:$A$126,MATCH($B28,Catálogo!$N$5:$N$126,0))="Acuáticas",INDEX(Catálogo!$B$5:$B$126,MATCH($B28,Catálogo!$N$5:$N$126,0)),INDEX(Catálogo!$A$5:$A$126,MATCH($B28,Catálogo!$N$5:$N$126,0))&" "&INDEX(Catálogo!$B$5:$B$126,MATCH($B28,Catálogo!$N$5:$N$126,0))),"") -> Suzuki DF115B/140B | D28: =IFERROR(INDEX(Catálogo!$C$5:$C$126,MATCH($B28,Catálogo!$N$5:$N$126,0))&" · "&INDEX(Catálogo!$D$5:$D$126,MATCH($B28,Catálogo!$N$5:$N$126,0)),"") -> 4T · 4 cil. | E28: =IFERROR(INDEX(Catálogo!$J$5:$J$126,MATCH($B28,Catálogo!$N$5:$N$126,0)),"") -> Confirmado
B29: 4 | C29: =IFERROR(IF(INDEX(Catálogo!$A$5:$A$126,MATCH($B29,Catálogo!$N$5:$N$126,0))="Acuáticas",INDEX(Catálogo!$B$5:$B$126,MATCH($B29,Catálogo!$N$5:$N$126,0)),INDEX(Catálogo!$A$5:$A$126,MATCH($B29,Catálogo!$N$5:$N$126,0))&" "&INDEX(Catálogo!$B$5:$B$126,MATCH($B29,Catálogo!$N$5:$N$126,0))),"") -> Yamaha F(L)115B (F115BETL/X, FL115BETX) | D29: =IFERROR(INDEX(Catálogo!$C$5:$C$126,MATCH($B29,Catálogo!$N$5:$N$126,0))&" · "&INDEX(Catálogo!$D$5:$D$126,MATCH($B29,Catálogo!$N$5:$N$126,0)),"") -> 4T · 4 cil., 1.832 cc | E29: =IFERROR(INDEX(Catálogo!$J$5:$J$126,MATCH($B29,Catálogo!$N$5:$N$126,0)),"") -> Confirmado
B30: 5 | C30: =IFERROR(IF(INDEX(Catálogo!$A$5:$A$126,MATCH($B30,Catálogo!$N$5:$N$126,0))="Acuáticas",INDEX(Catálogo!$B$5:$B$126,MATCH($B30,Catálogo!$N$5:$N$126,0)),INDEX(Catálogo!$A$5:$A$126,MATCH($B30,Catálogo!$N$5:$N$126,0))&" "&INDEX(Catálogo!$B$5:$B$126,MATCH($B30,Catálogo!$N$5:$N$126,0))),"") -> Parsun F-115 FEL-T-EFI / FEX-T-EFI | D30: =IFERROR(INDEX(Catálogo!$C$5:$C$126,MATCH($B30,Catálogo!$N$5:$N$126,0))&" · "&INDEX(Catálogo!$D$5:$D$126,MATCH($B30,Catálogo!$N$5:$N$126,0)),"") -> 4T · 4 cil., 1.832 cc | E30: =IFERROR(INDEX(Catálogo!$J$5:$J$126,MATCH($B30,Catálogo!$N$5:$N$126,0)),"") -> Por equivalencia
B31: 6 | C31: =IFERROR(IF(INDEX(Catálogo!$A$5:$A$126,MATCH($B31,Catálogo!$N$5:$N$126,0))="Acuáticas",INDEX(Catálogo!$B$5:$B$126,MATCH($B31,Catálogo!$N$5:$N$126,0)),INDEX(Catálogo!$A$5:$A$126,MATCH($B31,Catálogo!$N$5:$N$126,0))&" "&INDEX(Catálogo!$B$5:$B$126,MATCH($B31,Catálogo!$N$5:$N$126,0))),"") | D31: =IFERROR(INDEX(Catálogo!$C$5:$C$126,MATCH($B31,Catálogo!$N$5:$N$126,0))&" · "&INDEX(Catálogo!$D$5:$D$126,MATCH($B31,Catálogo!$N$5:$N$126,0)),"") | E31: =IFERROR(INDEX(Catálogo!$J$5:$J$126,MATCH($B31,Catálogo!$N$5:$N$126,0)),"")
B32: 7 | C32: =IFERROR(IF(INDEX(Catálogo!$A$5:$A$126,MATCH($B32,Catálogo!$N$5:$N$126,0))="Acuáticas",INDEX(Catálogo!$B$5:$B$126,MATCH($B32,Catálogo!$N$5:$N$126,0)),INDEX(Catálogo!$A$5:$A$126,MATCH($B32,Catálogo!$N$5:$N$126,0))&" "&INDEX(Catálogo!$B$5:$B$126,MATCH($B32,Catálogo!$N$5:$N$126,0))),"") | D32: =IFERROR(INDEX(Catálogo!$C$5:$C$126,MATCH($B32,Catálogo!$N$5:$N$126,0))&" · "&INDEX(Catálogo!$D$5:$D$126,MATCH($B32,Catálogo!$N$5:$N$126,0)),"") | E32: =IFERROR(INDEX(Catálogo!$J$5:$J$126,MATCH($B32,Catálogo!$N$5:$N$126,0)),"")
B33: 8 | C33: =IFERROR(IF(INDEX(Catálogo!$A$5:$A$126,MATCH($B33,Catálogo!$N$5:$N$126,0))="Acuáticas",INDEX(Catálogo!$B$5:$B$126,MATCH($B33,Catálogo!$N$5:$N$126,0)),INDEX(Catálogo!$A$5:$A$126,MATCH($B33,Catálogo!$N$5:$N$126,0))&" "&INDEX(Catálogo!$B$5:$B$126,MATCH($B33,Catálogo!$N$5:$N$126,0))),"") | D33: =IFERROR(INDEX(Catálogo!$C$5:$C$126,MATCH($B33,Catálogo!$N$5:$N$126,0))&" · "&INDEX(Catálogo!$D$5:$D$126,MATCH($B33,Catálogo!$N$5:$N$126,0)),"") | E33: =IFERROR(INDEX(Catálogo!$J$5:$J$126,MATCH($B33,Catálogo!$N$5:$N$126,0)),"")
B34: 9 | C34: =IFERROR(IF(INDEX(Catálogo!$A$5:$A$126,MATCH($B34,Catálogo!$N$5:$N$126,0))="Acuáticas",INDEX(Catálogo!$B$5:$B$126,MATCH($B34,Catálogo!$N$5:$N$126,0)),INDEX(Catálogo!$A$5:$A$126,MATCH($B34,Catálogo!$N$5:$N$126,0))&" "&INDEX(Catálogo!$B$5:$B$126,MATCH($B34,Catálogo!$N$5:$N$126,0))),"") | D34: =IFERROR(INDEX(Catálogo!$C$5:$C$126,MATCH($B34,Catálogo!$N$5:$N$126,0))&" · "&INDEX(Catálogo!$D$5:$D$126,MATCH($B34,Catálogo!$N$5:$N$126,0)),"") | E34: =IFERROR(INDEX(Catálogo!$J$5:$J$126,MATCH($B34,Catálogo!$N$5:$N$126,0)),"")
B35: 10 | C35: =IFERROR(IF(INDEX(Catálogo!$A$5:$A$126,MATCH($B35,Catálogo!$N$5:$N$126,0))="Acuáticas",INDEX(Catálogo!$B$5:$B$126,MATCH($B35,Catálogo!$N$5:$N$126,0)),INDEX(Catálogo!$A$5:$A$126,MATCH($B35,Catálogo!$N$5:$N$126,0))&" "&INDEX(Catálogo!$B$5:$B$126,MATCH($B35,Catálogo!$N$5:$N$126,0))),"") | D35: =IFERROR(INDEX(Catálogo!$C$5:$C$126,MATCH($B35,Catálogo!$N$5:$N$126,0))&" · "&INDEX(Catálogo!$D$5:$D$126,MATCH($B35,Catálogo!$N$5:$N$126,0)),"") | E35: =IFERROR(INDEX(Catálogo!$J$5:$J$126,MATCH($B35,Catálogo!$N$5:$N$126,0)),"")
B36: 11 | C36: =IFERROR(IF(INDEX(Catálogo!$A$5:$A$126,MATCH($B36,Catálogo!$N$5:$N$126,0))="Acuáticas",INDEX(Catálogo!$B$5:$B$126,MATCH($B36,Catálogo!$N$5:$N$126,0)),INDEX(Catálogo!$A$5:$A$126,MATCH($B36,Catálogo!$N$5:$N$126,0))&" "&INDEX(Catálogo!$B$5:$B$126,MATCH($B36,Catálogo!$N$5:$N$126,0))),"") | D36: =IFERROR(INDEX(Catálogo!$C$5:$C$126,MATCH($B36,Catálogo!$N$5:$N$126,0))&" · "&INDEX(Catálogo!$D$5:$D$126,MATCH($B36,Catálogo!$N$5:$N$126,0)),"") | E36: =IFERROR(INDEX(Catálogo!$J$5:$J$126,MATCH($B36,Catálogo!$N$5:$N$126,0)),"")
B37: 12 | C37: =IFERROR(IF(INDEX(Catálogo!$A$5:$A$126,MATCH($B37,Catálogo!$N$5:$N$126,0))="Acuáticas",INDEX(Catálogo!$B$5:$B$126,MATCH($B37,Catálogo!$N$5:$N$126,0)),INDEX(Catálogo!$A$5:$A$126,MATCH($B37,Catálogo!$N$5:$N$126,0))&" "&INDEX(Catálogo!$B$5:$B$126,MATCH($B37,Catálogo!$N$5:$N$126,0))),"") | D37: =IFERROR(INDEX(Catálogo!$C$5:$C$126,MATCH($B37,Catálogo!$N$5:$N$126,0))&" · "&INDEX(Catálogo!$D$5:$D$126,MATCH($B37,Catálogo!$N$5:$N$126,0)),"") | E37: =IFERROR(INDEX(Catálogo!$J$5:$J$126,MATCH($B37,Catálogo!$N$5:$N$126,0)),"")
... B40: 15 | C40: =IFERROR(IF(INDEX(Catálogo!$A$5:$A$126,MATCH($B40,Catálogo!$N$5:$N$126,0))="Acuáticas",INDEX(Catálogo!$B$5:$B$126,MATCH($B40,Catálogo!$N$5:$N$126,0)),INDEX(Catálogo!$A$5:$A$126,MATCH($B40,Catálogo!$N$5:$N$126,0))&" "&INDEX(Catálogo!$B$5:$B$126,MATCH($B40,Catálogo!$N$5:$N$126,0))),"") | D40: =IFERROR(INDEX(Catálogo!$C$5:$C$126,MATCH($B40,Catálogo!$N$5:$N$126,0))&" · "&INDEX(Catálogo!$D$5:$D$126,MATCH($B40,Catálogo!$N$5:$N$126,0)),"") | E40: =IFERROR(INDEX(Catálogo!$J$5:$J$126,MATCH($B40,Catálogo!$N$5:$N$126,0)),"")
B41: Se muestran hasta 15 modelos; el contador de arriba indica el total real.

Sheet Catálogo
A1: Catálogo de bujías NGK — motores fuera de borda y motos acuáticas en Colombia
A2: Consolidado de manuales y catálogos oficiales. La columna Confianza dice qué tan sólido es cada dato; filtra con las flechas del encabezado.
A4: Marca | B4: Modelo | C4: Tipo | D4: Motor | E4: Bujía NGK | F4: Gap (mm) | G4: Torque (N·m) | H4: Bujías por motor | I4: Mercado | J4: Confianza | K4: Fuente | L4: Notas | M4: Clave | N4: Aux. búsqueda
A5: Suzuki | B5: DF2.5S | C5: 4T | D5: 1 cil. | E5: CR6HSA | F5: 0.6–0.7 | G5: 11 | H5: 1 | I5: Venta actual | J5: Confirmado | K5: suzuki.com.co | L5: OEM 09482-00406 | M5: =A5&"|"&B5 -> Suzuki|DF2.5S | N5: =IF($E5=Consulta!$C$22,COUNTIF($E$5:$E5,Consulta!$C$22),"")
A6: Suzuki | B6: DF6AS | C6: 4T | D6: 1 cil. | E6: CPR6EA-9 | F6: 0.8–0.9 | G6: 10–12 | H6: 1 | I6: Venta actual | J6: Confirmado | K6: suzuki.com.co | M6: =A6&"|"&B6 -> Suzuki|DF6AS | N6: =IF($E6=Consulta!$C$22,COUNTIF($E$5:$E6,Consulta!$C$22),"")
A7: Suzuki | B7: DF20AS/AL | C7: 4T | D7: 2 cil. | E7: MR6K-9 | F7: 0.8–0.9 | G7: 11 | H7: 2 | I7: Venta actual | J7: Confirmado | K7: suzuki.com.co | M7: =A7&"|"&B7 -> Suzuki|DF20AS/AL | N7: =IF($E7=Consulta!$C$22,COUNTIF($E$5:$E7,Consulta!$C$22),"")
A8: Suzuki | B8: DF60AQHL/ATL | C8: 4T | D8: 4 cil. | E8: DCPR6E | F8: 0.8–0.9 | G8: 18 | H8: 4 | I8: Venta actual | J8: Confirmado | K8: suzuki.com.co | L8: OEM 09482-00446 | M8: =A8&"|"&B8 -> Suzuki|DF60AQHL/ATL | N8: =IF($E8=Consulta!$C$22,COUNTIF($E$5:$E8,Consulta!$C$22),"")
A9: Suzuki | B9: DF90ATL/ATX, DF90AWQHL/AWQHX | C9: 4T | D9: 4 cil. | E9: DCPR6E | F9: 0.8–0.9 | G9: 18 | H9: 4 | I9: Venta actual | J9: Confirmado | K9: suzuki.com.co | L9: OEM 09482-00446 | M9: =A9&"|"&B9 -> Suzuki|DF90ATL/ATX, DF90AWQHL/AWQHX | N9: =IF($E9=Consulta!$C$22,COUNTIF($E$5:$E9,Consulta!$C$22),"")
A10: Suzuki | B10: DF115BTL/BTX (Stealth/blanco) | C10: 4T | D10: 4 cil. | E10: LKR6E | F10: 0.8–0.9 | G10: 17 | H10: 4 | I10: Venta actual | J10: Confirmado | K10: suzuki.com.co | L10: OEM 09482-00649 | M10: =A10&"|"&B10 -> Suzuki|DF115BTL/BTX (Stealth/blanco) | N10: =IF($E10=Consulta!$C$22,COUNTIF($E$5:$E10,Consulta!$C$22),"") -> 1
A11: Suzuki | B11: DF150ATL/ATX/AZX | C11: 4T | D11: 4 cil. | E11: LKR6E | F11: 0.8–0.9 | G11: 17 | H11: 4 | I11: Venta actual | J11: Confirmado | K11: suzuki.com.co | L11: OEM 09482-00649 | M11: =A11&"|"&B11 -> Suzuki|DF150ATL/ATX/AZX | N11: =IF($E11=Consulta!$C$22,COUNTIF($E$5:$E11,Consulta!$C$22),"") -> 2
A12: Suzuki | B12: DF200TL/TX/ZX | C12: 4T | D12: V6, 3.614 cc | E12: BKR6E | F12: 0.7–0.8 | G12: 28 | H12: 6 | I12: Venta actual | J12: Confirmado | K12: suzuki.com.co | L12: OEM 09482-00427 | M12: =A12&"|"&B12 -> Suzuki|DF200TL/TX/ZX | N12: =IF($E12=Consulta!$C$22,COUNTIF($E$5:$E12,Consulta!$C$22),"")
A13: Suzuki | B13: DF250TX/ZX/TXX/ZXX | C13: 4T | D13: V6 | E13: BKR6E | F13: 0.7–0.8 | G13: 28 | H13: 6 | I13: Venta actual | J13: Confirmado | K13: suzuki.com.co | L13: OEM 09482-00427 | M13: =A13&"|"&B13 -> Suzuki|DF250TX/ZX/TXX/ZXX | N13: =IF($E13=Consulta!$C$22,COUNTIF($E$5:$E13,Consulta!$C$22),"")
A14: Suzuki | B14: DF300APX/APXX (Stealth/blanco) | C14: 4T | D14: V6 | E14: BKR6E | F14: 0.7–0.8 | G14: 28 | H14: 6 | I14: Venta actual | J14: Confirmado | K14: suzuki.com.co | L14: OEM 09482-00427 | M14: =A14&"|"&B14 -> Suzuki|DF300APX/APXX (Stealth/blanco) | N14: =IF($E14=Consulta!$C$22,COUNTIF($E$5:$E14,Consulta!$C$22),"")
A15: Suzuki | B15: DF325ATX/ATXX (blanco) | C15: 4T | D15: V6 | E15: ILZKR7D8 | F15: 0.7–0.8 | G15: 17 | H15: 6 | I15: Venta actual | J15: Confirmado | K15: suzuki.com.co | L15: Iridio. OEM 09482-00642 | M15: =A15&"|"&B15 -> Suzuki|DF325ATX/ATXX (blanco) | N15: =IF($E15=Consulta!$C$22,COUNTIF($E$5:$E15,Consulta!$C$22),"")
A16: Suzuki | B16: DT30S/L | C16: 2T | D16: 2 cil. | E16: BR7HS-10 | F16: 1.0 | H16: 2 | I16: Venta actual | J16: Confirmado | K16: suzuki.com.co | L16: Único 2T activo del catálogo. Con resistor. | M16: =A16&"|"&B16 -> Suzuki|DT30S/L | N16: =IF($E16=Consulta!$C$22,COUNTIF($E$5:$E16,Consulta!$C$22),"")
A17: Suzuki | B17: DF4/5/6 (2002–2010) | C17: 4T | D17: 1 cil. | E17: BPR6ES | F17: 0.7–0.8 | I17: Parque circulando | J17: Confirmado | K17: Manual Suzuki / NGK | M17: =A17&"|"&B17 -> Suzuki|DF4/5/6 (2002–2010) | N17: =IF($E17=Consulta!$C$22,COUNTIF($E$5:$E17,Consulta!$C$22),"")
A18: Suzuki | B18: DF4A/5A/6A (2011+) | C18: 4T | D18: 1 cil. | E18: CPR6EA-9 | F18: 0.8–0.9 | I18: Parque circulando | J18: Confirmado | K18: Manual Suzuki / NGK | M18: =A18&"|"&B18 -> Suzuki|DF4A/5A/6A (2011+) | N18: =IF($E18=Consulta!$C$22,COUNTIF($E$5:$E18,Consulta!$C$22),"")
A19: Suzuki | B19: DF8A/9.9A (2010+) | C19: 4T | D19: 2 cil. | E19: CR6E | F19: 0.7–0.8 | I19: Parque circulando | J19: Confirmado | K19: Manual Suzuki / NGK | M19: =A19&"|"&B19 -> Suzuki|DF8A/9.9A (2010+) | N19: =IF($E19=Consulta!$C$22,COUNTIF($E$5:$E19,Consulta!$C$22),"")
A20: Suzuki | B20: DF9.9/15 carburados (2005–2010) | C20: 4T | D20: 2 cil. | E20: BKR6E | F20: 0.7–0.8 | I20: Parque circulando | J20: Confirmado | K20: Manual Suzuki / NGK | M20: =A20&"|"&B20 -> Suzuki|DF9.9/15 carburados (2005–2010) | N20: =IF($E20=Consulta!$C$22,COUNTIF($E$5:$E20,Consulta!$C$22),"")
A21: Suzuki | B21: DF9.9B/15A/20A (2013–2017) | C21: 4T | D21: 2 cil. | E21: CPR6EA-9 | F21: 0.8–0.9 | I21: Parque circulando | J21: Confirmado | K21: Manual Suzuki / NGK | M21: =A21&"|"&B21 -> Suzuki|DF9.9B/15A/20A (2013–2017) | N21: =IF($E21=Consulta!$C$22,COUNTIF($E$5:$E21,Consulta!$C$22),"")
A22: Suzuki | B22: DF25/30 (2000–2004) | C22: 4T | D22: 3 cil. | E22: DCPR6E | F22: 0.7 | I22: Parque circulando | J22: Confirmado | K22: Manual Suzuki / NGK | M22: =A22&"|"&B22 -> Suzuki|DF25/30 (2000–2004) | N22: =IF($E22=Consulta!$C$22,COUNTIF($E$5:$E22,Consulta!$C$22),"")
A23: Suzuki | B23: DF40/50 y DF40A/50A | C23: 4T | D23: — | E23: DCPR6E | F23: 0.8–0.9 | I23: Parque circulando | J23: Confirmado | K23: Manual Suzuki / NGK | M23: =A23&"|"&B23 -> Suzuki|DF40/50 y DF40A/50A | N23: =IF($E23=Consulta!$C$22,COUNTIF($E$5:$E23,Consulta!$C$22),"")
A24: Suzuki | B24: DF60/70 (1998–2009) | C24: 4T | D24: — | E24: BPR6ES | F24: 0.7–0.8 | I24: Parque circulando | J24: Confirmado | K24: Manual Suzuki / NGK | M24: =A24&"|"&B24 -> Suzuki|DF60/70 (1998–2009) | N24: =IF($E24=Consulta!$C$22,COUNTIF($E$5:$E24,Consulta!$C$22),"")
A25: Suzuki | B25: DF70A/80A/90A/100B (2009+) | C25: 4T | D25: — | E25: DCPR6E | F25: 0.8–0.9 | I25: Parque circulando | J25: Confirmado | K25: Manual Suzuki / NGK | M25: =A25&"|"&B25 -> Suzuki|DF70A/80A/90A/100B (2009+) | N25: =IF($E25=Consulta!$C$22,COUNTIF($E$5:$E25,Consulta!$C$22),"")
A26: Suzuki | B26: DF90 sin 'A', DF100A/115A/140A | C26: 4T | D26: — | E26: BKR6E | F26: 0.7–0.8 | I26: Parque circulando | J26: Confirmado | K26: Manual Suzuki / NGK | M26: =A26&"|"&B26 -> Suzuki|DF90 sin 'A', DF100A/115A/140A | N26: =IF($E26=Consulta!$C$22,COUNTIF($E$5:$E26,Consulta!$C$22),"")
A27: Suzuki | B27: DF115B/140B | C27: 4T | D27: 4 cil. | E27: LKR6E | F27: 0.8–0.9 | I27: Parque circulando | J27: Confirmado | K27: Manual Suzuki / NGK | M27: =A27&"|"&B27 -> Suzuki|DF115B/140B | N27: =IF($E27=Consulta!$C$22,COUNTIF($E$5:$E27,Consulta!$C$22),"") -> 3
A28: Suzuki | B28: DF150/175 sin 'AP' | C28: 4T | D28: — | E28: BKR6E | F28: 0.7–0.8 | I28: Parque circulando | J28: Confirmado | K28: Manual Suzuki / NGK | M28: =A28&"|"&B28 -> Suzuki|DF150/175 sin 'AP' | N28: =IF($E28=Consulta!$C$22,COUNTIF($E$5:$E28,Consulta!$C$22),"")
A29: Suzuki | B29: DT2/2.2 | C29: 2T | D29: 1 cil. | E29: BR5HS | F29: 0.5–0.6 | I29: Parque circulando | J29: Confirmado | K29: Manual Suzuki / NGK | L29: Con resistor | M29: =A29&"|"&B29 -> Suzuki|DT2/2.2 | N29: =IF($E29=Consulta!$C$22,COUNTIF($E$5:$E29,Consulta!$C$22),"")
A30: Suzuki | B30: DT4/5/6/8 (desde 1986) | C30: 2T | D30: — | E30: BPR6HS | F30: 0.6 | I30: Parque circulando | J30: Confirmado | K30: Manual Suzuki / NGK | L30: Con resistor | M30: =A30&"|"&B30 -> Suzuki|DT4/5/6/8 (desde 1986) | N30: =IF($E30=Consulta!$C$22,COUNTIF($E$5:$E30,Consulta!$C$22),"")
A31: Suzuki | B31: DT9.9/15/16 (2 cil.) | C31: 2T | D31: 2 cil. | E31: BR7HS | F31: 0.7 | I31: Parque circulando | J31: Confirmado | K31: Manual Suzuki / NGK | L31: Con resistor | M31: =A31&"|"&B31 -> Suzuki|DT9.9/15/16 (2 cil.) | N31: =IF($E31=Consulta!$C$22,COUNTIF($E$5:$E31,Consulta!$C$22),"")
A32: Suzuki | B32: DT15C/E, DT20/25E/30 | C32: 2T | D32: — | E32: BR7HS-10 | F32: 1.0 | I32: Parque circulando | J32: Confirmado | K32: Manual Suzuki / NGK | L32: Con resistor | M32: =A32&"|"&B32 -> Suzuki|DT15C/E, DT20/25E/30 | N32: =IF($E32=Consulta!$C$22,COUNTIF($E$5:$E32,Consulta!$C$22),"")
A33: Suzuki | B33: DT40/50 | C33: 2T | D33: — | E33: BR8HS | F33: 0.7–0.8 | I33: Parque circulando | J33: Confirmado | K33: Manual Suzuki / NGK | L33: Con resistor | M33: =A33&"|"&B33 -> Suzuki|DT40/50 | N33: =IF($E33=Consulta!$C$22,COUNTIF($E$5:$E33,Consulta!$C$22),"")
A34: Suzuki | B34: DT55/60/75C | C34: 2T | D34: — | E34: BR8HS-10 | F34: 1.0 | I34: Parque circulando | J34: Confirmado | K34: Manual Suzuki / NGK | L34: Con resistor | M34: =A34&"|"&B34 -> Suzuki|DT55/60/75C | N34: =IF($E34=Consulta!$C$22,COUNTIF($E$5:$E34,Consulta!$C$22),"")
A35: Suzuki | B35: DT115/140 carburados | C35: 2T | D35: — | E35: BR8HS | F35: 0.7–0.8 | I35: Parque circulando | J35: Confirmado | K35: Manual Suzuki / NGK | L35: Con resistor | M35: =A35&"|"&B35 -> Suzuki|DT115/140 carburados | N35: =IF($E35=Consulta!$C$22,COUNTIF($E$5:$E35,Consulta!$C$22),"")
A36: Suzuki | B36: DT115S/140 EFI, DT150/175/200/225 V6 | C36: 2T | D36: — | E36: BR8HS-10 | F36: 1.0 | I36: Parque circulando | J36: Confirmado | K36: Manual Suzuki / NGK | L36: Con resistor | M36: =A36&"|"&B36 -> Suzuki|DT115S/140 EFI, DT150/175/200/225 V6 | N36: =IF($E36=Consulta!$C$22,COUNTIF($E$5:$E36,Consulta!$C$22),"")
A37: Yamaha | B37: F6C (F6CMHS-E) | C37: 4T | D37: 1 cil. | E37: CR6HSB | F37: 0.6–0.7 | H37: 1 | I37: Venta actual | J37: Confirmado | K37: Ficha Eduardoño | M37: =A37&"|"&B37 -> Yamaha|F6C (F6CMHS-E) | N37: =IF($E37=Consulta!$C$22,COUNTIF($E$5:$E37,Consulta!$C$22),"")
A38: Yamaha | B38: F20C (F20CMHS/HL-E) | C38: 4T | D38: 2 cil. | E38: DPR6EB-9 | F38: 0.8–0.9 | H38: 2 | I38: Venta actual | J38: Confirmado | K38: Ficha Eduardoño | L38: Parsun F-20 (mismo bloque) pide DPR7EA-9: no mezclar | M38: =A38&"|"&B38 -> Yamaha|F20C (F20CMHS/HL-E) | N38: =IF($E38=Consulta!$C$22,COUNTIF($E$5:$E38,Consulta!$C$22),"")
A39: Yamaha | B39: FT60J (FT60JEHDL/X, FT60JETL/X) | C39: 4T | D39: 4 cil., 996 cc | E39: DPR6EB-9 | F39: 0.8–0.9 | H39: 4 | I39: Venta actual | J39: Confirmado | K39: Ficha Eduardoño | M39: =A39&"|"&B39 -> Yamaha|FT60J (FT60JEHDL/X, FT60JETL/X) | N39: =IF($E39=Consulta!$C$22,COUNTIF($E$5:$E39,Consulta!$C$22),"")
A40: Yamaha | B40: F100G (F100GETL/X, F100GEHTL/X) | C40: 4T | D40: 4 cil., 1.832 cc | E40: LKR6E-9N | F40: 0.9 | H40: 4 | I40: Venta actual | J40: Confirmado | K40: Ficha Eduardoño | M40: =A40&"|"&B40 -> Yamaha|F100G (F100GETL/X, F100GEHTL/X) | N40: =IF($E40=Consulta!$C$22,COUNTIF($E$5:$E40,Consulta!$C$22),"")
A41: Yamaha | B41: F(L)115B (F115BETL/X, FL115BETX) | C41: 4T | D41: 4 cil., 1.832 cc | E41: LKR6E | F41: 0.9 | H41: 4 | I41: Venta actual | J41: Confirmado | K41: Ficha Eduardoño | M41: =A41&"|"&B41 -> Yamaha|F(L)115B (F115BETL/X, FL115BETX) | N41: =IF($E41=Consulta!$C$22,COUNTIF($E$5:$E41,Consulta!$C$22),"") -> 4
A42: Yamaha | B42: F(L)150F (F150FETX-E, FL150FETX-E) | C42: 4T | D42: 4 cil., 2.670 cc | E42: LFR5A-11 | F42: 1.0–1.1 | H42: 4 | I42: Venta actual | J42: Confirmado | K42: Ficha Eduardoño | M42: =A42&"|"&B42 -> Yamaha|F(L)150F (F150FETX-E, FL150FETX-E) | N42: =IF($E42=Consulta!$C$22,COUNTIF($E$5:$E42,Consulta!$C$22),"")
A43: Yamaha | B43: F(L)200B (F200BETX-E, FL200BETX-E) | C43: 4T | D43: V6, 3.352 cc | E43: LFR6A-11 | F43: 1.0–1.1 | H43: 6 | I43: Venta actual | J43: Confirmado | K43: Ficha Eduardoño | M43: =A43&"|"&B43 -> Yamaha|F(L)200B (F200BETX-E, FL200BETX-E) | N43: =IF($E43=Consulta!$C$22,COUNTIF($E$5:$E43,Consulta!$C$22),"")
A44: Yamaha | B44: F(L)200S (F200SETX, FL200SETX) | C44: 4T | D44: V6, 4.169 cc | E44: LFR6A-11 | F44: 1.0–1.1 | H44: 6 | I44: Venta actual | J44: Confirmado | K44: Ficha Eduardoño | M44: =A44&"|"&B44 -> Yamaha|F(L)200S (F200SETX, FL200SETX) | N44: =IF($E44=Consulta!$C$22,COUNTIF($E$5:$E44,Consulta!$C$22),"")
A45: Yamaha | B45: F250H (F250HETX/ETU, FL250HETX) | C45: 4T | D45: V6, 3.352 cc | E45: LFR6A-11 | F45: 1.0–1.1 | H45: 6 | I45: Venta actual | J45: Confirmado | K45: Ficha Eduardoño | M45: =A45&"|"&B45 -> Yamaha|F250H (F250HETX/ETU, FL250HETX) | N45: =IF($E45=Consulta!$C$22,COUNTIF($E$5:$E45,Consulta!$C$22),"")
A46: Yamaha | B46: F(L)250S (F250SETX, FL250SETX/ETU) | C46: 4T | D46: V6, 4.169 cc | E46: LFR6A-11 | F46: 1.0–1.1 | H46: 6 | I46: Venta actual | J46: Confirmado | K46: Ficha Eduardoño | M46: =A46&"|"&B46 -> Yamaha|F(L)250S (F250SETX, FL250SETX/ETU) | N46: =IF($E46=Consulta!$C$22,COUNTIF($E$5:$E46,Consulta!$C$22),"")
A47: Yamaha | B47: F(L)300D (F300DETX/ETU, FL300DETX/ETU) | C47: 4T | D47: V6, 4.169 cc | E47: LFR6A-11 | F47: 1.0–1.1 | H47: 6 | I47: Venta actual | J47: Confirmado | K47: Ficha Eduardoño | M47: =A47&"|"&B47 -> Yamaha|F(L)300D (F300DETX/ETU, FL300DETX/ETU) | N47: =IF($E47=Consulta!$C$22,COUNTIF($E$5:$E47,Consulta!$C$22),"")
A48: Yamaha | B48: F(L)300G (F300GETX/ETU, FL300GETX) | C48: 4T | D48: V6, 4.169 cc | E48: LFR6A-11 | F48: 1.0–1.1 | H48: 6 | I48: Venta actual | J48: Confirmado | K48: Ficha Eduardoño | M48: =A48&"|"&B48 -> Yamaha|F(L)300G (F300GETX/ETU, FL300GETX) | N48: =IF($E48=Consulta!$C$22,COUNTIF($E$5:$E48,Consulta!$C$22),"")
A49: Yamaha | B49: F350B V6 (F350BST) | C49: 4T | D49: V6, 4.256 cc | E49: ILMAR7E-9 | F49: 0.8–0.9 | H49: 6 | I49: Venta actual | J49: Confirmado | K49: Ficha Eduardoño | L49: Iridio | M49: =A49&"|"&B49 -> Yamaha|F350B V6 (F350BST) | N49: =IF($E49=Consulta!$C$22,COUNTIF($E$5:$E49,Consulta!$C$22),"")
A50: Yamaha | B50: E15D (E15DMHS/HL) | C50: 2T | D50: 2 cil., 246 cc | E50: B8HS-10 | F50: 1.0 | H50: 2 | I50: Venta actual | J50: Confirmado | K50: Ficha Eduardoño | L50: Mismo bloque que Parsun T-15 | M50: =A50&"|"&B50 -> Yamaha|E15D (E15DMHS/HL) | N50: =IF($E50=Consulta!$C$22,COUNTIF($E$5:$E50,Consulta!$C$22),"")
A51: Yamaha | B51: E40J (E40JMHS/HL) | C51: 2T | D51: 2 cil., 669 cc | E51: B7HS | F51: 0.6–0.7 | H51: 2 | I51: Venta actual | J51: Confirmado | K51: Ficha Eduardoño | L51: Mismo bloque que Parsun T-40 | M51: =A51&"|"&B51 -> Yamaha|E40J (E40JMHS/HL) | N51: =IF($E51=Consulta!$C$22,COUNTIF($E$5:$E51,Consulta!$C$22),"")
A52: Yamaha | B52: E40X (E40XMHS/HL-E) | C52: 2T | D52: 2 cil. | E52: B7HS | F52: 0.7 | H52: 2 | I52: Venta actual | J52: Confirmado | K52: NGK Part Finder | L52: La ficha de Eduardoño no abrió | M52: =A52&"|"&B52 -> Yamaha|E40X (E40XMHS/HL-E) | N52: =IF($E52=Consulta!$C$22,COUNTIF($E$5:$E52,Consulta!$C$22),"")
A53: Yamaha | B53: E75B (E75BMHDL/X) | C53: 2T | D53: 3 cil., 1.140 cc | E53: B8HS-10 | F53: 1.0 | H53: 3 | I53: Venta actual | J53: Confirmado | K53: Ficha Eduardoño | L53: Mismo bloque que Parsun T-75 | M53: =A53&"|"&B53 -> Yamaha|E75B (E75BMHDL/X) | N53: =IF($E53=Consulta!$C$22,COUNTIF($E$5:$E53,Consulta!$C$22),"")
A54: Yamaha | B54: F15 (histórico) | C54: 4T | D54: 2 cil. | E54: DPR6EA-9 | F54: 0.8 | I54: Parque circulando | J54: Verificar año/serie | K54: Histórico Yamaha / NGK | M54: =A54&"|"&B54 -> Yamaha|F15 (histórico) | N54: =IF($E54=Consulta!$C$22,COUNTIF($E$5:$E54,Consulta!$C$22),"")
A55: Yamaha | B55: F15C / F20 carburados | C55: 4T | D55: 2 cil. | E55: DPR6EB-9 | F55: 0.8–0.9 | I55: Parque circulando | J55: Verificar año/serie | K55: Histórico Yamaha / NGK | M55: =A55&"|"&B55 -> Yamaha|F15C / F20 carburados | N55: =IF($E55=Consulta!$C$22,COUNTIF($E$5:$E55,Consulta!$C$22),"")
A56: Yamaha | B56: F40 / F50 / F60 (histórico) | C56: 4T | D56: — | E56: DPR6EB-9 | F56: 0.9 | I56: Parque circulando | J56: Verificar año/serie | K56: Histórico Yamaha / NGK | L56: Algunos FT60 usan DPR5EA-9 | M56: =A56&"|"&B56 -> Yamaha|F40 / F50 / F60 (histórico) | N56: =IF($E56=Consulta!$C$22,COUNTIF($E$5:$E56,Consulta!$C$22),"")
A57: Yamaha | B57: F75 / F80 / F90 / F100 (histórico) | C57: 4T | D57: 4 cil. | E57: LFR5A-11 | F57: 1.0–1.1 | I57: Parque circulando | J57: Verificar año/serie | K57: Histórico Yamaha / NGK | M57: =A57&"|"&B57 -> Yamaha|F75 / F80 / F90 / F100 (histórico) | N57: =IF($E57=Consulta!$C$22,COUNTIF($E$5:$E57,Consulta!$C$22),"")
A58: Yamaha | B58: F115 (2000–2013) | C58: 4T | D58: 4 cil. | E58: LFR6A-11 | F58: 1.1 | I58: Parque circulando | J58: Verificar año/serie | K58: Histórico Yamaha / NGK | M58: =A58&"|"&B58 -> Yamaha|F115 (2000–2013) | N58: =IF($E58=Consulta!$C$22,COUNTIF($E$5:$E58,Consulta!$C$22),"")
A59: Yamaha | B59: F200 / F225 (3.3 L V6, histórico) | C59: 4T | D59: V6 | E59: LFR5A-11 | F59: 1.0–1.1 | I59: Parque circulando | J59: Verificar año/serie | K59: Histórico Yamaha / NGK | L59: F200A en adelante usan LFR6A-11 | M59: =A59&"|"&B59 -> Yamaha|F200 / F225 (3.3 L V6, histórico) | N59: =IF($E59=Consulta!$C$22,COUNTIF($E$5:$E59,Consulta!$C$22),"")
A60: Yamaha | B60: 2T 4–5 HP (histórico) | C60: 2T | D60: 1 cil. | E60: B7HS | F60: 0.6 | I60: Parque circulando | J60: Verificar año/serie | K60: Histórico Yamaha / NGK | M60: =A60&"|"&B60 -> Yamaha|2T 4–5 HP (histórico) | N60: =IF($E60=Consulta!$C$22,COUNTIF($E$5:$E60,Consulta!$C$22),"")
A61: Yamaha | B61: 2T 6–8 HP (histórico) | C61: 2T | D61: — | E61: B7HS-10 | F61: 0.9 | I61: Parque circulando | J61: Verificar año/serie | K61: Histórico Yamaha / NGK | M61: =A61&"|"&B61 -> Yamaha|2T 6–8 HP (histórico) | N61: =IF($E61=Consulta!$C$22,COUNTIF($E$5:$E61,Consulta!$C$22),"")
A62: Yamaha | B62: 2T 9.9–40 HP (histórico) | C62: 2T | D62: — | E62: B7HS-10 | F62: 1.0 | I62: Parque circulando | J62: Verificar año/serie | K62: Histórico Yamaha / NGK | M62: =A62&"|"&B62 -> Yamaha|2T 9.9–40 HP (histórico) | N62: =IF($E62=Consulta!$C$22,COUNTIF($E$5:$E62,Consulta!$C$22),"")
A63: Yamaha | B63: 2T 50–75 HP (histórico) | C63: 2T | D63: — | E63: B8HS-10 | F63: 1.0 | I63: Parque circulando | J63: Verificar año/serie | K63: Histórico Yamaha / NGK | M63: =A63&"|"&B63 -> Yamaha|2T 50–75 HP (histórico) | N63: =IF($E63=Consulta!$C$22,COUNTIF($E$5:$E63,Consulta!$C$22),"")
A64: Yamaha | B64: 2T 115 HP (histórico) | C64: 2T | D64: 4 cil. | E64: BR8HS-10 | F64: 1.0 | I64: Parque circulando | J64: Verificar año/serie | K64: Histórico Yamaha / NGK | M64: =A64&"|"&B64 -> Yamaha|2T 115 HP (histórico) | N64: =IF($E64=Consulta!$C$22,COUNTIF($E$5:$E64,Consulta!$C$22),"")
A65: Mercury | B65: FourStroke 2.5 / 3.5 | C65: 4T | D65: 1 cil. | E65: DCPR6E | F65: 0.84 (0.033") | I65: Mixto (verificar año) | J65: Confirmado | K65: Tabla oficial Mercury 2022 | M65: =A65&"|"&B65 -> Mercury|FourStroke 2.5 / 3.5 | N65: =IF($E65=Consulta!$C$22,COUNTIF($E$5:$E65,Consulta!$C$22),"")
A66: Mercury | B66: FourStroke 4 / 5 / 6 | C66: 4T | D66: 1 cil. | E66: DCPR6E | F66: 0.9 (0.035") | I66: Mixto (verificar año) | J66: Confirmado | K66: Tabla oficial Mercury 2022 | M66: =A66&"|"&B66 -> Mercury|FourStroke 4 / 5 / 6 | N66: =IF($E66=Consulta!$C$22,COUNTIF($E$5:$E66,Consulta!$C$22),"")
A67: Mercury | B67: FourStroke 8 / 9.9 / 15 / 20 (serie JPN nueva) | C67: 4T | D67: 2 cil. | E67: DCPR6E | F67: 0.84 (0.033") | I67: Mixto (verificar año) | J67: Confirmado | K67: Tabla oficial Mercury 2022 | M67: =A67&"|"&B67 -> Mercury|FourStroke 8 / 9.9 / 15 / 20 (serie JPN nueva) | N67: =IF($E67=Consulta!$C$22,COUNTIF($E$5:$E67,Consulta!$C$22),"")
A68: Mercury | B68: FourStroke 8 / 9.9 / 15 / 25 / 30 carburados (USA/BEL ant.) | C68: 4T | D68: — | E68: DPR6EA-9 | F68: 0.9 (0.035") | I68: Mixto (verificar año) | J68: Confirmado | K68: Tabla oficial Mercury 2022 | M68: =A68&"|"&B68 -> Mercury|FourStroke 8 / 9.9 / 15 / 25 / 30 carburados (USA/BEL ant.) | N68: =IF($E68=Consulta!$C$22,COUNTIF($E$5:$E68,Consulta!$C$22),"")
A69: Mercury | B69: FourStroke 40 / 50 / 60 carburados | C69: 4T | D69: — | E69: DPR6EA-9 | F69: 0.9 (0.035") | I69: Mixto (verificar año) | J69: Confirmado | K69: Tabla oficial Mercury 2022 | M69: =A69&"|"&B69 -> Mercury|FourStroke 40 / 50 / 60 carburados | N69: =IF($E69=Consulta!$C$22,COUNTIF($E$5:$E69,Consulta!$C$22),"")
A70: Mercury | B70: FourStroke 40 / 50 / 60 EFI | C70: 4T | D70: — | E70: DCPR7E | F70: 0.7 | I70: Mixto (verificar año) | J70: Por equivalencia | K70: Tabla oficial Mercury 2022 | L70: OEM Mercury: Champion RA8HC (0.040"). NGK lista DCPR7E | M70: =A70&"|"&B70 -> Mercury|FourStroke 40 / 50 / 60 EFI | N70: =IF($E70=Consulta!$C$22,COUNTIF($E$5:$E70,Consulta!$C$22),"")
A71: Mercury | B71: FourStroke 75 / 90 de 1.596 cc (antiguo) | C71: 4T | D71: 4 cil., 1.596 cc | E71: LFR5A-11 | F71: 1.1 (0.043") | I71: Mixto (verificar año) | J71: Confirmado | K71: Tabla oficial Mercury 2022 | M71: =A71&"|"&B71 -> Mercury|FourStroke 75 / 90 de 1.596 cc (antiguo) | N71: =IF($E71=Consulta!$C$22,COUNTIF($E$5:$E71,Consulta!$C$22),"")
A72: Mercury | B72: FourStroke 75–115 de 1.7 L | C72: 4T | D72: 4 cil. | E72: LFR4A-E | F72: 0.8 (0.032") | I72: Mixto (verificar año) | J72: Confirmado | K72: Tabla oficial Mercury 2022 | M72: =A72&"|"&B72 -> Mercury|FourStroke 75–115 de 1.7 L | N72: =IF($E72=Consulta!$C$22,COUNTIF($E$5:$E72,Consulta!$C$22),"")
A73: Mercury | B73: FourStroke 75–115 de 2.1 L y Pro XS 115 | C73: 4T | D73: 4 cil. | E73: ZFR5F | F73: 0.8 (0.032") | I73: Mixto (verificar año) | J73: Confirmado | K73: Tabla oficial Mercury 2022 | M73: =A73&"|"&B73 -> Mercury|FourStroke 75–115 de 2.1 L y Pro XS 115 | N73: =IF($E73=Consulta!$C$22,COUNTIF($E$5:$E73,Consulta!$C$22),"")
A74: Mercury | B74: FourStroke 115 EFI de 1.741 cc (antiguo) | C74: 4T | D74: 4 cil. | E74: LFR6A-11 | F74: 1.0 (0.041") | I74: Mixto (verificar año) | J74: Confirmado | K74: Tabla oficial Mercury 2022 | M74: =A74&"|"&B74 -> Mercury|FourStroke 115 EFI de 1.741 cc (antiguo) | N74: =IF($E74=Consulta!$C$22,COUNTIF($E$5:$E74,Consulta!$C$22),"")
A75: Mercury | B75: FourStroke 150 EFI | C75: 4T | D75: 4 cil. | E75: ZFR5F | F75: 0.8 (0.032") | I75: Mixto (verificar año) | J75: Confirmado | K75: Tabla oficial Mercury 2022 | M75: =A75&"|"&B75 -> Mercury|FourStroke 150 EFI | N75: =IF($E75=Consulta!$C$22,COUNTIF($E$5:$E75,Consulta!$C$22),"")
A76: Mercury | B76: FourStroke 225 EFI de 3.0 L | C76: 4T | D76: V6 | E76: LFR5A-11 | F76: 1.1 (0.043") | I76: Mixto (verificar año) | J76: Confirmado | K76: Tabla oficial Mercury 2022 | M76: =A76&"|"&B76 -> Mercury|FourStroke 225 EFI de 3.0 L | N76: =IF($E76=Consulta!$C$22,COUNTIF($E$5:$E76,Consulta!$C$22),"")
A77: Mercury | B77: 175–300 V6/V8 y 450R (serie 2B529482+) | C77: 4T | D77: V6/V8 | E77: LART7C-9 | F77: 0.9 (0.035") | I77: Mixto (verificar año) | J77: Confirmado | K77: Tabla oficial Mercury 2022 | M77: =A77&"|"&B77 -> Mercury|175–300 V6/V8 y 450R (serie 2B529482+) | N77: =IF($E77=Consulta!$C$22,COUNTIF($E$5:$E77,Consulta!$C$22),"")
A78: Mercury | B78: Verado 135–350 | C78: 4T | D78: — | E78: ILFR6GE | F78: 0.8 (0.031") | I78: Mixto (verificar año) | J78: Confirmado | K78: Tabla oficial Mercury 2022 | L78: Iridio | M78: =A78&"|"&B78 -> Mercury|Verado 135–350 | N78: =IF($E78=Consulta!$C$22,COUNTIF($E$5:$E78,Consulta!$C$22),"")
A79: Mercury | B79: TwoStroke 2.5 / 3.3 / 3.5 | C79: 2T | D79: 1 cil. | E79: BPR6HS-10 | F79: 1.0 (0.040") | I79: Mixto (verificar año) | J79: Confirmado | K79: Tabla oficial Mercury 2022 | L79: Con resistor | M79: =A79&"|"&B79 -> Mercury|TwoStroke 2.5 / 3.3 / 3.5 | N79: =IF($E79=Consulta!$C$22,COUNTIF($E$5:$E79,Consulta!$C$22),"")
A80: Mercury | B80: TwoStroke 3.6 / 4 / 5 | C80: 2T | D80: 1 cil. | E80: BPR7HS-10 | F80: 1.0 (0.040") | I80: Mixto (verificar año) | J80: Confirmado | K80: Tabla oficial Mercury 2022 | L80: Con resistor | M80: =A80&"|"&B80 -> Mercury|TwoStroke 3.6 / 4 / 5 | N80: =IF($E80=Consulta!$C$22,COUNTIF($E$5:$E80,Consulta!$C$22),"")
A81: Mercury | B81: TwoStroke 6 / 8 / 9.9 (hasta 0G112449) | C81: 2T | D81: — | E81: BPZ8H-N-10 | F81: 1.0 (0.040") | I81: Mixto (verificar año) | J81: Confirmado | K81: Tabla oficial Mercury 2022 | M81: =A81&"|"&B81 -> Mercury|TwoStroke 6 / 8 / 9.9 (hasta 0G112449) | N81: =IF($E81=Consulta!$C$22,COUNTIF($E$5:$E81,Consulta!$C$22),"")
A82: Mercury | B82: TwoStroke 9.9 / 10 / 15 (series nuevas) y Sea Pro 15 | C82: 2T | D82: — | E82: BPZ8HS-15 | F82: 1.5 (0.060") | I82: Mixto (verificar año) | J82: Confirmado | K82: Tabla oficial Mercury 2022 | M82: =A82&"|"&B82 -> Mercury|TwoStroke 9.9 / 10 / 15 (series nuevas) y Sea Pro 15 | N82: =IF($E82=Consulta!$C$22,COUNTIF($E$5:$E82,Consulta!$C$22),"")
A83: Mercury | B83: TwoStroke 15 Super / Sea Pro XD / 18 / 20 / 25 | C83: 2T | D83: — | E83: BPZ8H-N-10 | F83: 1.0 (0.040") | I83: Mixto (verificar año) | J83: Confirmado | K83: Tabla oficial Mercury 2022 | M83: =A83&"|"&B83 -> Mercury|TwoStroke 15 Super / Sea Pro XD / 18 / 20 / 25 | N83: =IF($E83=Consulta!$C$22,COUNTIF($E$5:$E83,Consulta!$C$22),"")
A84: Mercury | B84: TwoStroke 30 / 40 / 50 / 55 / 60 (3 cil., desde 0D000750) | C84: 2T | D84: 3 cil. | E84: BPZ8H-N-10 | F84: 1.0 (0.040") | I84: Mixto (verificar año) | J84: Confirmado | K84: Tabla oficial Mercury 2022 | M84: =A84&"|"&B84 -> Mercury|TwoStroke 30 / 40 / 50 / 55 / 60 (3 cil., desde 0D000750) | N84: =IF($E84=Consulta!$C$22,COUNTIF($E$5:$E84,Consulta!$C$22),"")
A85: Mercury | B85: TwoStroke 100 / 115 / 125 (4 cil.) | C85: 2T | D85: 4 cil. | E85: BPZ8H-N-10 | F85: 1.0 (0.040") | I85: Mixto (verificar año) | J85: Confirmado | K85: Tabla oficial Mercury 2022 | M85: =A85&"|"&B85 -> Mercury|TwoStroke 100 / 115 / 125 (4 cil.) | N85: =IF($E85=Consulta!$C$22,COUNTIF($E$5:$E85,Consulta!$C$22),"")
A86: Mercury | B86: TwoStroke V6 150–300 (desde 0G960500) | C86: 2T | D86: V6 | E86: BPZ8HS-10 | F86: 1.0 (0.040") | I86: Mixto (verificar año) | J86: Confirmado | K86: Tabla oficial Mercury 2022 | M86: =A86&"|"&B86 -> Mercury|TwoStroke V6 150–300 (desde 0G960500) | N86: =IF($E86=Consulta!$C$22,COUNTIF($E$5:$E86,Consulta!$C$22),"")
A87: Mercury | B87: OptiMax 75 / 90 / 115 (1.5 L, 3 cil.) | C87: 2T | D87: 3 cil. | E87: IZFR5J | F87: 0.8 (0.032") | I87: Mixto (verificar año) | J87: Confirmado | K87: Tabla oficial Mercury 2022 | M87: =A87&"|"&B87 -> Mercury|OptiMax 75 / 90 / 115 (1.5 L, 3 cil.) | N87: =IF($E87=Consulta!$C$22,COUNTIF($E$5:$E87,Consulta!$C$22),"")
A88: Mercury | B88: OptiMax V6 DFI 135–225 y Pro XS 200 | C88: 2T | D88: V6 | E88: IZFR5G | F88: 0.8 (0.032") | I88: Mixto (verificar año) | J88: Confirmado | K88: Tabla oficial Mercury 2022 | M88: =A88&"|"&B88 -> Mercury|OptiMax V6 DFI 135–225 y Pro XS 200 | N88: =IF($E88=Consulta!$C$22,COUNTIF($E$5:$E88,Consulta!$C$22),"")
A89: Mercury | B89: OptiMax Pro XS 150–250 | C89: 2T | D89: V6 | E89: IZFR6J | F89: 1.1 (0.042") | I89: Mixto (verificar año) | J89: Confirmado | K89: Tabla oficial Mercury 2022 | M89: =A89&"|"&B89 -> Mercury|OptiMax Pro XS 150–250 | N89: =IF($E89=Consulta!$C$22,COUNTIF($E$5:$E89,Consulta!$C$22),"")
A90: Mercury | B90: V6 antiguos carburados 135–300 HP | C90: 2T | D90: V6 | E90: BUZ8H | F90: Superficie | I90: Mixto (verificar año) | J90: Confirmado | K90: Tabla oficial Mercury 2022 | L90: BUZHW en algunas series. No se calibran | M90: =A90&"|"&B90 -> Mercury|V6 antiguos carburados 135–300 HP | N90: =IF($E90=Consulta!$C$22,COUNTIF($E$5:$E90,Consulta!$C$22),"")
A91: Parsun | B91: F-2.6 BMS | C91: 4T | D91: 1 cil. | E91: BR6HS | F91: 0.6–0.7 | H91: 1 | I91: Venta actual | J91: Confirmado | K91: Surtiminas + parsun.eu | M91: =A91&"|"&B91 -> Parsun|F-2.6 BMS | N91: =IF($E91=Consulta!$C$22,COUNTIF($E$5:$E91,Consulta!$C$22),"")
A92: Parsun | B92: F-5 BMS / BML | C92: 4T | D92: 1 cil., 112 cc | E92: BR6HS | F92: 0.6–0.7 | H92: 1 | I92: Venta actual | J92: Confirmado | K92: Surtiminas + parsun.eu | L92: Serie F4/F5. Las F5A/F6A usan CR6HSA | M92: =A92&"|"&B92 -> Parsun|F-5 BMS / BML | N92: =IF($E92=Consulta!$C$22,COUNTIF($E$5:$E92,Consulta!$C$22),"")
A93: Parsun | B93: F-20 EBMS / EBML | C93: 4T | D93: 2 cil., 362 cc | E93: DPR7EA-9 | F93: 0.8–0.9 | H93: 2 | I93: Venta actual | J93: Confirmado | K93: Surtiminas + parsun.eu | L93: Yamaha F20C (mismo bloque) usa DPR6EB-9: un grado más frío en Parsun | M93: =A93&"|"&B93 -> Parsun|F-20 EBMS / EBML | N93: =IF($E93=Consulta!$C$22,COUNTIF($E$5:$E93,Consulta!$C$22),"")
A94: Parsun | B94: F-50 BEL-D-EFI / BEL-T-EFI / FEL-T-EFI | C94: 4T | D94: 4 cil., 996 cc | E94: DPR7EA-9 | F94: 0.8–0.9 | G94: 18 | H94: 4 | I94: Venta actual | J94: Confirmado | K94: Surtiminas + parsun.eu | M94: =A94&"|"&B94 -> Parsun|F-50 BEL-D-EFI / BEL-T-EFI / FEL-T-EFI | N94: =IF($E94=Consulta!$C$22,COUNTIF($E$5:$E94,Consulta!$C$22),"")
A95: Parsun | B95: F-60 BEL-D-EFI / BEL-T-EFI / FEL-T-EFI | C95: 4T | D95: 4 cil., 996 cc | E95: DPR7EA-9 | F95: 0.8–0.9 | G95: 18 | H95: 4 | I95: Venta actual | J95: Confirmado | K95: Surtiminas + parsun.eu | M95: =A95&"|"&B95 -> Parsun|F-60 BEL-D-EFI / BEL-T-EFI / FEL-T-EFI | N95: =IF($E95=Consulta!$C$22,COUNTIF($E$5:$E95,Consulta!$C$22),"")
A96: Parsun | B96: F-115 FEL-T-EFI / FEX-T-EFI | C96: 4T | D96: 4 cil., 1.832 cc | E96: LKR6E | F96: 0.9 | H96: 4 | I96: Venta actual | J96: Por equivalencia | K96: Surtiminas + equivalencia | L96: Mismo bloque que Yamaha F115B. Sin manual Parsun: verificar con la bujía de fábrica | M96: =A96&"|"&B96 -> Parsun|F-115 FEL-T-EFI / FEX-T-EFI | N96: =IF($E96=Consulta!$C$22,COUNTIF($E$5:$E96,Consulta!$C$22),"") -> 5
A97: Parsun | B97: LT7 'peque peque' (motor 170F) | C97: 4T | D97: 1 cil., 208 cc | E97: BPR6ES | F97: 0.7–0.8 | H97: 1 | I97: Venta actual | J97: Verificar | K97: Surtiminas | L97: No es un fuera de borda Parsun. BPR6ES es la referencia habitual de los clones GX200 | M97: =A97&"|"&B97 -> Parsun|LT7 'peque peque' (motor 170F) | N97: =IF($E97=Consulta!$C$22,COUNTIF($E$5:$E97,Consulta!$C$22),"")
A98: Parsun | B98: T-2C BMS | C98: 2T | D98: — | E98: BPR7HS | F98: 0.7 | I98: Venta actual | J98: Por equivalencia | K98: Surtiminas (modelo) + parsun.eu y distribuidor NZ (bujía) | L98: Por equivalencia con la serie T2.6 | M98: =A98&"|"&B98 -> Parsun|T-2C BMS | N98: =IF($E98=Consulta!$C$22,COUNTIF($E$5:$E98,Consulta!$C$22),"")
A99: Parsun | B99: T-3.6 BMS | C99: 2T | D99: — | E99: BPR7HS-10 | F99: 1.0 | I99: Venta actual | J99: Confirmado | K99: Surtiminas (modelo) + parsun.eu y distribuidor NZ (bujía) | M99: =A99&"|"&B99 -> Parsun|T-3.6 BMS | N99: =IF($E99=Consulta!$C$22,COUNTIF($E$5:$E99,Consulta!$C$22),"")
A100: Parsun | B100: T-5 BMS / BML | C100: 2T | D100: — | E100: BPR7HS-10 | F100: 1.0 | I100: Venta actual | J100: Por equivalencia | K100: Surtiminas (modelo) + parsun.eu y distribuidor NZ (bujía) | L100: Por equivalencia con la serie T5.8 | M100: =A100&"|"&B100 -> Parsun|T-5 BMS / BML | N100: =IF($E100=Consulta!$C$22,COUNTIF($E$5:$E100,Consulta!$C$22),"")
A101: Parsun | B101: T-9.8 BMS / BML | C101: 2T | D101: 2 cil., 169 cc | E101: BPR7HS | F101: 0.7 | H101: 2 | I101: Venta actual | J101: Confirmado | K101: Surtiminas + NGK | M101: =A101&"|"&B101 -> Parsun|T-9.8 BMS / BML | N101: =IF($E101=Consulta!$C$22,COUNTIF($E$5:$E101,Consulta!$C$22),"")
...

Sheet Cotizador
B1: Cotizador de bujías por motor
B2: Elige marca y modelo por línea; el libro calcula bujías por motor, precio de lista, descuento e IVA.
B4: Cliente | C4: Taller Náutico El Remo (ejemplo) | E4: Cómo usar: 1) escribe el cliente y elige su tipo 2) en cada línea elige marca y modelo 3) escribe cuántos motores 4) revisa el estado (columna M).
B5: Tipo | C5: Taller | E5: La línea 1 es un ejemplo con precio ilustrativo (ver Precios y Stock). Bórrala o sobrescríbela. 'Ajuste manual' sirve cuando el catálogo no trae el número de bujías.
B6: Fecha | C6: =TODAY() -> 46307
B7: Vendedor
B11: Marca | C11: Modelo | D11: Bujía NGK | E11: Bujías por motor | F11: Ajuste manual | G11: Nº motores | H11: Total bujías | I11: Precio de lista | J11: Precio manual | K11: Precio aplicado | L11: Subtotal (COP) | M11: Estado
B12: Suzuki | C12: DF60AQHL/ATL | D12: =IF(O12="","",IF(O12=0,"—",INDEX(Catálogo!$E$5:$E$126,O12))) -> DCPR6E | E12: =IF(OR(O12="",O12=0),"",IF(INDEX(Catálogo!$H$5:$H$126,O12)="","",INDEX(Catálogo!$H$5:$H$126,O12))) -> 4 | G12: 2 | H12: =IF(NOT(ISNUMBER(G12)),0,G12*IF(ISNUMBER(F12),F12,IF(ISNUMBER(E12),E12,0))) -> 8 | I12: =IF(OR(D12="",D12="—"),"",IFERROR(INDEX('Precios y Stock'!$G$5:$G$56,MATCH(D12,'Precios y Stock'!$A$5:$A$56,0)),"")) -> 30000 | K12: =IF(ISNUMBER(J12),J12,I12) -> 30000 | L12: =IF(AND(ISNUMBER(K12),H12>0),H12*K12,0) -> 240000 | M12: =IF(C12="","",IF(O12=0,"Modelo no encontrado",IF(AND(NOT(ISNUMBER(F12)),NOT(ISNUMBER(E12))),"Define bujías por motor",IF(NOT(ISNUMBER(G12)),"Falta nº de motores",IF(NOT(ISNUMBER(K12)),"Falta precio","OK"))))) -> OK | O12: =IF(C12="","",IFERROR(MATCH(B12&"|"&C12,Catálogo!$M$5:$M$126,0),0)) -> 4
D13: =IF(O13="","",IF(O13=0,"—",INDEX(Catálogo!$E$5:$E$126,O13))) | E13: =IF(OR(O13="",O13=0),"",IF(INDEX(Catálogo!$H$5:$H$126,O13)="","",INDEX(Catálogo!$H$5:$H$126,O13))) | H13: =IF(NOT(ISNUMBER(G13)),0,G13*IF(ISNUMBER(F13),F13,IF(ISNUMBER(E13),E13,0))) -> 0 | I13: =IF(OR(D13="",D13="—"),"",IFERROR(INDEX('Precios y Stock'!$G$5:$G$56,MATCH(D13,'Precios y Stock'!$A$5:$A$56,0)),"")) | K13: =IF(ISNUMBER(J13),J13,I13) | L13: =IF(AND(ISNUMBER(K13),H13>0),H13*K13,0) -> 0 | M13: =IF(C13="","",IF(O13=0,"Modelo no encontrado",IF(AND(NOT(ISNUMBER(F13)),NOT(ISNUMBER(E13))),"Define bujías por motor",IF(NOT(ISNUMBER(G13)),"Falta nº de motores",IF(NOT(ISNUMBER(K13)),"Falta precio","OK"))))) | O13: =IF(C13="","",IFERROR(MATCH(B13&"|"&C13,Catálogo!$M$5:$M$126,0),0))
D14: =IF(O14="","",IF(O14=0,"—",INDEX(Catálogo!$E$5:$E$126,O14))) | E14: =IF(OR(O14="",O14=0),"",IF(INDEX(Catálogo!$H$5:$H$126,O14)="","",INDEX(Catálogo!$H$5:$H$126,O14))) | H14: =IF(NOT(ISNUMBER(G14)),0,G14*IF(ISNUMBER(F14),F14,IF(ISNUMBER(E14),E14,0))) -> 0 | I14: =IF(OR(D14="",D14="—"),"",IFERROR(INDEX('Precios y Stock'!$G$5:$G$56,MATCH(D14,'Precios y Stock'!$A$5:$A$56,0)),"")) | K14: =IF(ISNUMBER(J14),J14,I14) | L14: =IF(AND(ISNUMBER(K14),H14>0),H14*K14,0) -> 0 | M14: =IF(C14="","",IF(O14=0,"Modelo no encontrado",IF(AND(NOT(ISNUMBER(F14)),NOT(ISNUMBER(E14))),"Define bujías por motor",IF(NOT(ISNUMBER(G14)),"Falta nº de motores",IF(NOT(ISNUMBER(K14)),"Falta precio","OK"))))) | O14: =IF(C14="","",IFERROR(MATCH(B14&"|"&C14,Catálogo!$M$5:$M$126,0),0))
D15: =IF(O15="","",IF(O15=0,"—",INDEX(Catálogo!$E$5:$E$126,O15))) | E15: =IF(OR(O15="",O15=0),"",IF(INDEX(Catálogo!$H$5:$H$126,O15)="","",INDEX(Catálogo!$H$5:$H$126,O15))) | H15: =IF(NOT(ISNUMBER(G15)),0,G15*IF(ISNUMBER(F15),F15,IF(ISNUMBER(E15),E15,0))) -> 0 | I15: =IF(OR(D15="",D15="—"),"",IFERROR(INDEX('Precios y Stock'!$G$5:$G$56,MATCH(D15,'Precios y Stock'!$A$5:$A$56,0)),"")) | K15: =IF(ISNUMBER(J15),J15,I15) | L15: =IF(AND(ISNUMBER(K15),H15>0),H15*K15,0) -> 0 | M15: =IF(C15="","",IF(O15=0,"Modelo no encontrado",IF(AND(NOT(ISNUMBER(F15)),NOT(ISNUMBER(E15))),"Define bujías por motor",IF(NOT(ISNUMBER(G15)),"Falta nº de motores",IF(NOT(ISNUMBER(K15)),"Falta precio","OK"))))) | O15: =IF(C15="","",IFERROR(MATCH(B15&"|"&C15,Catálogo!$M$5:$M$126,0),0))
D16: =IF(O16="","",IF(O16=0,"—",INDEX(Catálogo!$E$5:$E$126,O16))) | E16: =IF(OR(O16="",O16=0),"",IF(INDEX(Catálogo!$H$5:$H$126,O16)="","",INDEX(Catálogo!$H$5:$H$126,O16))) | H16: =IF(NOT(ISNUMBER(G16)),0,G16*IF(ISNUMBER(F16),F16,IF(ISNUMBER(E16),E16,0))) -> 0 | I16: =IF(OR(D16="",D16="—"),"",IFERROR(INDEX('Precios y Stock'!$G$5:$G$56,MATCH(D16,'Precios y Stock'!$A$5:$A$56,0)),"")) | K16: =IF(ISNUMBER(J16),J16,I16) | L16: =IF(AND(ISNUMBER(K16),H16>0),H16*K16,0) -> 0 | M16: =IF(C16="","",IF(O16=0,"Modelo no encontrado",IF(AND(NOT(ISNUMBER(F16)),NOT(ISNUMBER(E16))),"Define bujías por motor",IF(NOT(ISNUMBER(G16)),"Falta nº de motores",IF(NOT(ISNUMBER(K16)),"Falta precio","OK"))))) | O16: =IF(C16="","",IFERROR(MATCH(B16&"|"&C16,Catálogo!$M$5:$M$126,0),0))
D17: =IF(O17="","",IF(O17=0,"—",INDEX(Catálogo!$E$5:$E$126,O17))) | E17: =IF(OR(O17="",O17=0),"",IF(INDEX(Catálogo!$H$5:$H$126,O17)="","",INDEX(Catálogo!$H$5:$H$126,O17))) | H17: =IF(NOT(ISNUMBER(G17)),0,G17*IF(ISNUMBER(F17),F17,IF(ISNUMBER(E17),E17,0))) -> 0 | I17: =IF(OR(D17="",D17="—"),"",IFERROR(INDEX('Precios y Stock'!$G$5:$G$56,MATCH(D17,'Precios y Stock'!$A$5:$A$56,0)),"")) | K17: =IF(ISNUMBER(J17),J17,I17) | L17: =IF(AND(ISNUMBER(K17),H17>0),H17*K17,0) -> 0 | M17: =IF(C17="","",IF(O17=0,"Modelo no encontrado",IF(AND(NOT(ISNUMBER(F17)),NOT(ISNUMBER(E17))),"Define bujías por motor",IF(NOT(ISNUMBER(G17)),"Falta nº de motores",IF(NOT(ISNUMBER(K17)),"Falta precio","OK"))))) | O17: =IF(C17="","",IFERROR(MATCH(B17&"|"&C17,Catálogo!$M$5:$M$126,0),0))
D18: =IF(O18="","",IF(O18=0,"—",INDEX(Catálogo!$E$5:$E$126,O18))) | E18: =IF(OR(O18="",O18=0),"",IF(INDEX(Catálogo!$H$5:$H$126,O18)="","",INDEX(Catálogo!$H$5:$H$126,O18))) | H18: =IF(NOT(ISNUMBER(G18)),0,G18*IF(ISNUMBER(F18),F18,IF(ISNUMBER(E18),E18,0))) -> 0 | I18: =IF(OR(D18="",D18="—"),"",IFERROR(INDEX('Precios y Stock'!$G$5:$G$56,MATCH(D18,'Precios y Stock'!$A$5:$A$56,0)),"")) | K18: =IF(ISNUMBER(J18),J18,I18) | L18: =IF(AND(ISNUMBER(K18),H18>0),H18*K18,0) -> 0 | M18: =IF(C18="","",IF(O18=0,"Modelo no encontrado",IF(AND(NOT(ISNUMBER(F18)),NOT(ISNUMBER(E18))),"Define bujías por motor",IF(NOT(ISNUMBER(G18)),"Falta nº de motores",IF(NOT(ISNUMBER(K18)),"Falta precio","OK"))))) | O18: =IF(C18="","",IFERROR(MATCH(B18&"|"&C18,Catálogo!$M$5:$M$126,0),0))
D19: =IF(O19="","",IF(O19=0,"—",INDEX(Catálogo!$E$5:$E$126,O19))) | E19: =IF(OR(O19="",O19=0),"",IF(INDEX(Catálogo!$H$5:$H$126,O19)="","",INDEX(Catálogo!$H$5:$H$126,O19))) | H19: =IF(NOT(ISNUMBER(G19)),0,G19*IF(ISNUMBER(F19),F19,IF(ISNUMBER(E19),E19,0))) -> 0 | I19: =IF(OR(D19="",D19="—"),"",IFERROR(INDEX('Precios y Stock'!$G$5:$G$56,MATCH(D19,'Precios y Stock'!$A$5:$A$56,0)),"")) | K19: =IF(ISNUMBER(J19),J19,I19) | L19: =IF(AND(ISNUMBER(K19),H19>0),H19*K19,0) -> 0 | M19: =IF(C19="","",IF(O19=0,"Modelo no encontrado",IF(AND(NOT(ISNUMBER(F19)),NOT(ISNUMBER(E19))),"Define bujías por motor",IF(NOT(ISNUMBER(G19)),"Falta nº de motores",IF(NOT(ISNUMBER(K19)),"Falta precio","OK"))))) | O19: =IF(C19="","",IFERROR(MATCH(B19&"|"&C19,Catálogo!$M$5:$M$126,0),0))
D20: =IF(O20="","",IF(O20=0,"—",INDEX(Catálogo!$E$5:$E$126,O20))) | E20: =IF(OR(O20="",O20=0),"",IF(INDEX(Catálogo!$H$5:$H$126,O20)="","",INDEX(Catálogo!$H$5:$H$126,O20))) | H20: =IF(NOT(ISNUMBER(G20)),0,G20*IF(ISNUMBER(F20),F20,IF(ISNUMBER(E20),E20,0))) -> 0 | I20: =IF(OR(D20="",D20="—"),"",IFERROR(INDEX('Precios y Stock'!$G$5:$G$56,MATCH(D20,'Precios y Stock'!$A$5:$A$56,0)),"")) | K20: =IF(ISNUMBER(J20),J20,I20) | L20: =IF(AND(ISNUMBER(K20),H20>0),H20*K20,0) -> 0 | M20: =IF(C20="","",IF(O20=0,"Modelo no encontrado",IF(AND(NOT(ISNUMBER(F20)),NOT(ISNUMBER(E20))),"Define bujías por motor",IF(NOT(ISNUMBER(G20)),"Falta nº de motores",IF(NOT(ISNUMBER(K20)),"Falta precio","OK"))))) | O20: =IF(C20="","",IFERROR(MATCH(B20&"|"&C20,Catálogo!$M$5:$M$126,0),0))
D21: =IF(O21="","",IF(O21=0,"—",INDEX(Catálogo!$E$5:$E$126,O21))) | E21: =IF(OR(O21="",O21=0),"",IF(INDEX(Catálogo!$H$5:$H$126,O21)="","",INDEX(Catálogo!$H$5:$H$126,O21))) | H21: =IF(NOT(ISNUMBER(G21)),0,G21*IF(ISNUMBER(F21),F21,IF(ISNUMBER(E21),E21,0))) -> 0 | I21: =IF(OR(D21="",D21="—"),"",IFERROR(INDEX('Precios y Stock'!$G$5:$G$56,MATCH(D21,'Precios y Stock'!$A$5:$A$56,0)),"")) | K21: =IF(ISNUMBER(J21),J21,I21) | L21: =IF(AND(ISNUMBER(K21),H21>0),H21*K21,0) -> 0 | M21: =IF(C21="","",IF(O21=0,"Modelo no encontrado",IF(AND(NOT(ISNUMBER(F21)),NOT(ISNUMBER(E21))),"Define bujías por motor",IF(NOT(ISNUMBER(G21)),"Falta nº de motores",IF(NOT(ISNUMBER(K21)),"Falta precio","OK"))))) | O21: =IF(C21="","",IFERROR(MATCH(B21&"|"&C21,Catálogo!$M$5:$M$126,0),0))
D22: =IF(O22="","",IF(O22=0,"—",INDEX(Catálogo!$E$5:$E$126,O22))) | E22: =IF(OR(O22="",O22=0),"",IF(INDEX(Catálogo!$H$5:$H$126,O22)="","",INDEX(Catálogo!$H$5:$H$126,O22))) | H22: =IF(NOT(ISNUMBER(G22)),0,G22*IF(ISNUMBER(F22),F22,IF(ISNUMBER(E22),E22,0))) -> 0 | I22: =IF(OR(D22="",D22="—"),"",IFERROR(INDEX('Precios y Stock'!$G$5:$G$56,MATCH(D22,'Precios y Stock'!$A$5:$A$56,0)),"")) | K22: =IF(ISNUMBER(J22),J22,I22) | L22: =IF(AND(ISNUMBER(K22),H22>0),H22*K22,0) -> 0 | M22: =IF(C22="","",IF(O22=0,"Modelo no encontrado",IF(AND(NOT(ISNUMBER(F22)),NOT(ISNUMBER(E22))),"Define bujías por motor",IF(NOT(ISNUMBER(G22)),"Falta nº de motores",IF(NOT(ISNUMBER(K22)),"Falta precio","OK"))))) | O22: =IF(C22="","",IFERROR(MATCH(B22&"|"&C22,Catálogo!$M$5:$M$126,0),0))
D23: =IF(O23="","",IF(O23=0,"—",INDEX(Catálogo!$E$5:$E$126,O23))) | E23: =IF(OR(O23="",O23=0),"",IF(INDEX(Catálogo!$H$5:$H$126,O23)="","",INDEX(Catálogo!$H$5:$H$126,O23))) | H23: =IF(NOT(ISNUMBER(G23)),0,G23*IF(ISNUMBER(F23),F23,IF(ISNUMBER(E23),E23,0))) -> 0 | I23: =IF(OR(D23="",D23="—"),"",IFERROR(INDEX('Precios y Stock'!$G$5:$G$56,MATCH(D23,'Precios y Stock'!$A$5:$A$56,0)),"")) | K23: =IF(ISNUMBER(J23),J23,I23) | L23: =IF(AND(ISNUMBER(K23),H23>0),H23*K23,0) -> 0 | M23: =IF(C23="","",IF(O23=0,"Modelo no encontrado",IF(AND(NOT(ISNUMBER(F23)),NOT(ISNUMBER(E23))),"Define bujías por motor",IF(NOT(ISNUMBER(G23)),"Falta nº de motores",IF(NOT(ISNUMBER(K23)),"Falta precio","OK"))))) | O23: =IF(C23="","",IFERROR(MATCH(B23&"|"&C23,Catálogo!$M$5:$M$126,0),0))
B25: Precios en pesos colombianos (COP). Descuento según el tipo de cliente definido en Parámetros. | J25: Total de bujías | L25: =SUM(H12:H23) -> 8
J26: Subtotal bruto | L26: =SUM(L12:L23) -> 240000
J27: Descuento | K27: =IFERROR(INDEX(Parámetros!$B$10:$B$12,MATCH($C$5,Parámetros!$A$10:$A$12,0)),0) -> 0.1 | L27: =-ROUND(L26*K27,0) -> -24000
J28: Subtotal neto | L28: =L26+L27 -> 216000
L29: =ROUND(L28*K29,0) -> 0
J30: TOTAL A PAGAR | L30: =L28+L29 -> 216000

Sheet Precios y Stock
A1: Precios y stock por referencia NGK
A2: Una fila por bujía distinta. Escribe tu costo y tu stock actual (celdas amarillas); el resto se calcula con los Parámetros.
A4: Bujía NGK | B4: Tipo | C4: Modelos en catálogo | D4: De ellos, venta actual | E4: Prioridad | F4: Costo unitario (COP) | G4: Precio de lista (COP) | H4: Stock actual (und) | I4: Stock mínimo sugerido | J4: Reponer (und) | K4: Valor a reponer a costo (COP) | L4: Ranking de cobertura
A5: DCPR6E | B5: Estándar | C5: =COUNTIF(Catálogo!$E$5:$E$126,A5) -> 8 | D5: =COUNTIFS(Catálogo!$E$5:$E$126,A5,Catálogo!$I$5:$I$126,"Venta actual") -> 2 | E5: =IF(C5>=Parámetros!$B$15,"Alta",IF(C5>=Parámetros!$B$16,"Media","Baja")) -> Alta | F5: 15000 | G5: =IF(F5="","",ROUND(F5/(1-Parámetros!$B$5)/Parámetros!$B$7,0)*Parámetros!$B$7) -> 30000 | I5: =IF(E5="Alta",Parámetros!$B$19,IF(E5="Media",Parámetros!$B$20,Parámetros!$B$21)) -> 12 | J5: =MAX(0,I5-N(H5)) -> 12 | K5: =IF(F5="","",J5*F5) -> 180000 | L5: =RANK(C5,$C$5:$C$56)+COUNTIF($C$5:C5,C5)-1 -> 1
A6: LFR6A-11 | B6: Estándar | C6: =COUNTIF(Catálogo!$E$5:$E$126,A6) -> 8 | D6: =COUNTIFS(Catálogo!$E$5:$E$126,A6,Catálogo!$I$5:$I$126,"Venta actual") -> 6 | E6: =IF(C6>=Parámetros!$B$15,"Alta",IF(C6>=Parámetros!$B$16,"Media","Baja")) -> Alta | G6: =IF(F6="","",ROUND(F6/(1-Parámetros!$B$5)/Parámetros!$B$7,0)*Parámetros!$B$7) | I6: =IF(E6="Alta",Parámetros!$B$19,IF(E6="Media",Parámetros!$B$20,Parámetros!$B$21)) -> 12 | J6: =MAX(0,I6-N(H6)) -> 12 | K6: =IF(F6="","",J6*F6) | L6: =RANK(C6,$C$5:$C$56)+COUNTIF($C$5:C6,C6)-1 -> 2
A7: BKR6E | B7: Estándar | C7: =COUNTIF(Catálogo!$E$5:$E$126,A7) -> 6 | D7: =COUNTIFS(Catálogo!$E$5:$E$126,A7,Catálogo!$I$5:$I$126,"Venta actual") -> 3 | E7: =IF(C7>=Parámetros!$B$15,"Alta",IF(C7>=Parámetros!$B$16,"Media","Baja")) -> Alta | F7: 6500 | G7: =IF(F7="","",ROUND(F7/(1-Parámetros!$B$5)/Parámetros!$B$7,0)*Parámetros!$B$7) -> 13000 | I7: =IF(E7="Alta",Parámetros!$B$19,IF(E7="Media",Parámetros!$B$20,Parámetros!$B$21)) -> 12 | J7: =MAX(0,I7-N(H7)) -> 12 | K7: =IF(F7="","",J7*F7) -> 78000 | L7: =RANK(C7,$C$5:$C$56)+COUNTIF($C$5:C7,C7)-1 -> 3
A8: DPR7EA-9 | B8: Estándar | C8: =COUNTIF(Catálogo!$E$5:$E$126,A8) -> 6 | D8: =COUNTIFS(Catálogo!$E$5:$E$126,A8,Catálogo!$I$5:$I$126,"Venta actual") -> 3 | E8: =IF(C8>=Parámetros!$B$15,"Alta",IF(C8>=Parámetros!$B$16,"Media","Baja")) -> Alta | G8: =IF(F8="","",ROUND(F8/(1-Parámetros!$B$5)/Parámetros!$B$7,0)*Parámetros!$B$7) | I8: =IF(E8="Alta",Parámetros!$B$19,IF(E8="Media",Parámetros!$B$20,Parámetros!$B$21)) -> 12 | J8: =MAX(0,I8-N(H8)) -> 12 | K8: =IF(F8="","",J8*F8) | L8: =RANK(C8,$C$5:$C$56)+COUNTIF($C$5:C8,C8)-1 -> 4
A9: BPR7HS | B9: Estándar | C9: =COUNTIF(Catálogo!$E$5:$E$126,A9) -> 5 | D9: =COUNTIFS(Catálogo!$E$5:$E$126,A9,Catálogo!$I$5:$I$126,"Venta actual") -> 5 | E9: =IF(C9>=Parámetros!$B$15,"Alta",IF(C9>=Parámetros!$B$16,"Media","Baja")) -> Alta | G9: =IF(F9="","",ROUND(F9/(1-Parámetros!$B$5)/Parámetros!$B$7,0)*Parámetros!$B$7) | I9: =IF(E9="Alta",Parámetros!$B$19,IF(E9="Media",Parámetros!$B$20,Parámetros!$B$21)) -> 12 | J9: =MAX(0,I9-N(H9)) -> 12 | K9: =IF(F9="","",J9*F9) | L9: =RANK(C9,$C$5:$C$56)+COUNTIF($C$5:C9,C9)-1 -> 5
A10: LFR5A-11 | B10: Estándar | C10: =COUNTIF(Catálogo!$E$5:$E$126,A10) -> 5 | D10: =COUNTIFS(Catálogo!$E$5:$E$126,A10,Catálogo!$I$5:$I$126,"Venta actual") -> 1 | E10: =IF(C10>=Parámetros!$B$15,"Alta",IF(C10>=Parámetros!$B$16,"Media","Baja")) -> Alta | F10: 9500 | G10: =IF(F10="","",ROUND(F10/(1-Parámetros!$B$5)/Parámetros!$B$7,0)*Parámetros!$B$7) -> 19000 | I10: =IF(E10="Alta",Parámetros!$B$19,IF(E10="Media",Parámetros!$B$20,Parámetros!$B$21)) -> 12 | J10: =MAX(0,I10-N(H10)) -> 12 | K10: =IF(F10="","",J10*F10) -> 114000 | L10: =RANK(C10,$C$5:$C$56)+COUNTIF($C$5:C10,C10)-1 -> 6
A11: LKR6E | B11: Estándar | C11: =COUNTIF(Catálogo!$E$5:$E$126,A11) -> 5 | D11: =COUNTIFS(Catálogo!$E$5:$E$126,A11,Catálogo!$I$5:$I$126,"Venta actual") -> 4 | E11: =IF(C11>=Parámetros!$B$15,"Alta",IF(C11>=Parámetros!$B$16,"Media","Baja")) -> Alta | G11: =IF(F11="","",ROUND(F11/(1-Parámetros!$B$5)/Parámetros!$B$7,0)*Parámetros!$B$7) | I11: =IF(E11="Alta",Parámetros!$B$19,IF(E11="Media",Parámetros!$B$20,Parámetros!$B$21)) -> 12 | J11: =MAX(0,I11-N(H11)) -> 12 | K11: =IF(F11="","",J11*F11) | L11: =RANK(C11,$C$5:$C$56)+COUNTIF($C$5:C11,C11)-1 -> 7
A12: BPZ8H-N-10 | B12: Estándar | C12: =COUNTIF(Catálogo!$E$5:$E$126,A12) -> 4 | D12: =COUNTIFS(Catálogo!$E$5:$E$126,A12,Catálogo!$I$5:$I$126,"Venta actual") -> 0 | E12: =IF(C12>=Parámetros!$B$15,"Alta",IF(C12>=Parámetros!$B$16,"Media","Baja")) -> Media | G12: =IF(F12="","",ROUND(F12/(1-Parámetros!$B$5)/Parámetros!$B$7,0)*Parámetros!$B$7) | I12: =IF(E12="Alta",Parámetros!$B$19,IF(E12="Media",Parámetros!$B$20,Parámetros!$B$21)) -> 8 | J12: =MAX(0,I12-N(H12)) -> 8 | K12: =IF(F12="","",J12*F12) | L12: =RANK(C12,$C$5:$C$56)+COUNTIF($C$5:C12,C12)-1 -> 8
A13: BR8HS-10 | B13: Estándar | C13: =COUNTIF(Catálogo!$E$5:$E$126,A13) -> 4 | D13: =COUNTIFS(Catálogo!$E$5:$E$126,A13,Catálogo!$I$5:$I$126,"Venta actual") -> 1 | E13: =IF(C13>=Parámetros!$B$15,"Alta",IF(C13>=Parámetros!$B$16,"Media","Baja")) -> Media | F13: 5200 | G13: =IF(F13="","",ROUND(F13/(1-Parámetros!$B$5)/Parámetros!$B$7,0)*Parámetros!$B$7) -> 10400 | I13: =IF(E13="Alta",Parámetros!$B$19,IF(E13="Media",Parámetros!$B$20,Parámetros!$B$21)) -> 8 | J13: =MAX(0,I13-N(H13)) -> 8 | K13: =IF(F13="","",J13*F13) -> 41600 | L13: =RANK(C13,$C$5:$C$56)+COUNTIF($C$5:C13,C13)-1 -> 9
A14: DCPR8E | B14: Estándar | C14: =COUNTIF(Catálogo!$E$5:$E$126,A14) -> 4 | D14: =COUNTIFS(Catálogo!$E$5:$E$126,A14,Catálogo!$I$5:$I$126,"Venta actual") -> 2 | E14: =IF(C14>=Parámetros!$B$15,"Alta",IF(C14>=Parámetros!$B$16,"Media","Baja")) -> Media | G14: =IF(F14="","",ROUND(F14/(1-Parámetros!$B$5)/Parámetros!$B$7,0)*Parámetros!$B$7) | I14: =IF(E14="Alta",Parámetros!$B$19,IF(E14="Media",Parámetros!$B$20,Parámetros!$B$21)) -> 8 | J14: =MAX(0,I14-N(H14)) -> 8 | K14: =IF(F14="","",J14*F14) | L14: =RANK(C14,$C$5:$C$56)+COUNTIF($C$5:C14,C14)-1 -> 10
A15: DPR6EA-9 | B15: Estándar | C15: =COUNTIF(Catálogo!$E$5:$E$126,A15) -> 4 | D15: =COUNTIFS(Catálogo!$E$5:$E$126,A15,Catálogo!$I$5:$I$126,"Venta actual") -> 0 | E15: =IF(C15>=Parámetros!$B$15,"Alta",IF(C15>=Parámetros!$B$16,"Media","Baja")) -> Media | F15: 6200 | G15: =IF(F15="","",ROUND(F15/(1-Parámetros!$B$5)/Parámetros!$B$7,0)*Parámetros!$B$7) -> 12400 | I15: =IF(E15="Alta",Parámetros!$B$19,IF(E15="Media",Parámetros!$B$20,Parámetros!$B$21)) -> 8 | J15: =MAX(0,I15-N(H15)) -> 8 | K15: =IF(F15="","",J15*F15) -> 49600 | L15: =RANK(C15,$C$5:$C$56)+COUNTIF($C$5:C15,C15)-1 -> 11
A16: DPR6EB-9 | B16: Estándar | C16: =COUNTIF(Catálogo!$E$5:$E$126,A16) -> 4 | D16: =COUNTIFS(Catálogo!$E$5:$E$126,A16,Catálogo!$I$5:$I$126,"Venta actual") -> 2 | E16: =IF(C16>=Parámetros!$B$15,"Alta",IF(C16>=Parámetros!$B$16,"Media","Baja")) -> Media | G16: =IF(F16="","",ROUND(F16/(1-Parámetros!$B$5)/Parámetros!$B$7,0)*Parámetros!$B$7) | I16: =IF(E16="Alta",Parámetros!$B$19,IF(E16="Media",Parámetros!$B$20,Parámetros!$B$21)) -> 8 | J16: =MAX(0,I16-N(H16)) -> 8 | K16: =IF(F16="","",J16*F16) | L16: =RANK(C16,$C$5:$C$56)+COUNTIF($C$5:C16,C16)-1 -> 12
A17: B7HS | B17: Estándar | C17: =COUNTIF(Catálogo!$E$5:$E$126,A17) -> 3 | D17: =COUNTIFS(Catálogo!$E$5:$E$126,A17,Catálogo!$I$5:$I$126,"Venta actual") -> 2 | E17: =IF(C17>=Parámetros!$B$15,"Alta",IF(C17>=Parámetros!$B$16,"Media","Baja")) -> Media | G17: =IF(F17="","",ROUND(F17/(1-Parámetros!$B$5)/Parámetros!$B$7,0)*Parámetros!$B$7) | I17: =IF(E17="Alta",Parámetros!$B$19,IF(E17="Media",Parámetros!$B$20,Parámetros!$B$21)) -> 8 | J17: =MAX(0,I17-N(H17)) -> 8 | K17: =IF(F17="","",J17*F17) | L17: =RANK(C17,$C$5:$C$56)+COUNTIF($C$5:C17,C17)-1 -> 13
A18: B8HS-10 | B18: Estándar | C18: =COUNTIF(Catálogo!$E$5:$E$126,A18) -> 3 | D18: =COUNTIFS(Catálogo!$E$5:$E$126,A18,Catálogo!$I$5:$I$126,"Venta actual") -> 2 | E18: =IF(C18>=Parámetros!$B$15,"Alta",IF(C18>=Parámetros!$B$16,"Media","Baja")) -> Media | F18: 5200 | G18: =IF(F18="","",ROUND(F18/(1-Parámetros!$B$5)/Parámetros!$B$7,0)*Parámetros!$B$7) -> 10400 | I18: =IF(E18="Alta",Parámetros!$B$19,IF(E18="Media",Parámetros!$B$20,Parámetros!$B$21)) -> 8 | J18: =MAX(0,I18-N(H18)) -> 8 | K18: =IF(F18="","",J18*F18) -> 41600 | L18: =RANK(C18,$C$5:$C$56)+COUNTIF($C$5:C18,C18)-1 -> 14
A19: BPR6ES | B19: Estándar | C19: =COUNTIF(Catálogo!$E$5:$E$126,A19) -> 3 | D19: =COUNTIFS(Catálogo!$E$5:$E$126,A19,Catálogo!$I$5:$I$126,"Venta actual") -> 1 | E19: =IF(C19>=Parámetros!$B$15,"Alta",IF(C19>=Parámetros!$B$16,"Media","Baja")) -> Media | G19: =IF(F19="","",ROUND(F19/(1-Parámetros!$B$5)/Parámetros!$B$7,0)*Parámetros!$B$7) | I19: =IF(E19="Alta",Parámetros!$B$19,IF(E19="Media",Parámetros!$B$20,Parámetros!$B$21)) -> 8 | J19: =MAX(0,I19-N(H19)) -> 8 | K19: =IF(F19="","",J19*F19) | L19: =RANK(C19,$C$5:$C$56)+COUNTIF($C$5:C19,C19)-1 -> 15
A20: BPR7HS-10 | B20: Estándar | C20: =COUNTIF(Catálogo!$E$5:$E$126,A20) -> 3 | D20: =COUNTIFS(Catálogo!$E$5:$E$126,A20,Catálogo!$I$5:$I$126,"Venta actual") -> 2 | E20: =IF(C20>=Parámetros!$B$15,"Alta",IF(C20>=Parámetros!$B$16,"Media","Baja")) -> Media | G20: =IF(F20="","",ROUND(F20/(1-Parámetros!$B$5)/Parámetros!$B$7,0)*Parámetros!$B$7) | I20: =IF(E20="Alta",Parámetros!$B$19,IF(E20="Media",Parámetros!$B$20,Parámetros!$B$21)) -> 8 | J20: =MAX(0,I20-N(H20)) -> 8 | K20: =IF(F20="","",J20*F20) | L20: =RANK(C20,$C$5:$C$56)+COUNTIF($C$5:C20,C20)-1 -> 16
A21: CPR6EA-9 | B21: Estándar | C21: =COUNTIF(Catálogo!$E$5:$E$126,A21) -> 3 | D21: =COUNTIFS(Catálogo!$E$5:$E$126,A21,Catálogo!$I$5:$I$126,"Venta actual") -> 1 | E21: =IF(C21>=Parámetros!$B$15,"Alta",IF(C21>=Parámetros!$B$16,"Media","Baja")) -> Media | G21: =IF(F21="","",ROUND(F21/(1-Parámetros!$B$5)/Parámetros!$B$7,0)*Parámetros!$B$7) | I21: =IF(E21="Alta",Parámetros!$B$19,IF(E21="Media",Parámetros!$B$20,Parámetros!$B$21)) -> 8 | J21: =MAX(0,I21-N(H21)) -> 8 | K21: =IF(F21="","",J21*F21) | L21: =RANK(C21,$C$5:$C$56)+COUNTIF($C$5:C21,C21)-1 -> 17
A22: B7HS-10 | B22: Estándar | C22: =COUNTIF(Catálogo!$E$5:$E$126,A22) -> 2 | D22: =COUNTIFS(Catálogo!$E$5:$E$126,A22,Catálogo!$I$5:$I$126,"Venta actual") -> 0 | E22: =IF(C22>=Parámetros!$B$15,"Alta",IF(C22>=Parámetros!$B$16,"Media","Baja")) -> Baja | F22: 5200 | G22: =IF(F22="","",ROUND(F22/(1-Parámetros!$B$5)/Parámetros!$B$7,0)*Parámetros!$B$7) -> 10400 | I22: =IF(E22="Alta",Parámetros!$B$19,IF(E22="Media",Parámetros!$B$20,Parámetros!$B$21)) -> 4 | J22: =MAX(0,I22-N(H22)) -> 4 | K22: =IF(F22="","",J22*F22) -> 20800 | L22: =RANK(C22,$C$5:$C$56)+COUNTIF($C$5:C22,C22)-1 -> 18
A23: BR6HS | B23: Estándar | C23: =COUNTIF(Catálogo!$E$5:$E$126,A23) -> 2 | D23: =COUNTIFS(Catálogo!$E$5:$E$126,A23,Catálogo!$I$5:$I$126,"Venta actual") -> 2 | E23: =IF(C23>=Parámetros!$B$15,"Alta",IF(C23>=Parámetros!$B$16,"Media","Baja")) -> Baja | G23: =IF(F23="","",ROUND(F23/(1-Parámetros!$B$5)/Parámetros!$B$7,0)*Parámetros!$B$7) | I23: =IF(E23="Alta",Parámetros!$B$19,IF(E23="Media",Parámetros!$B$20,Parámetros!$B$21)) -> 4 | J23: =MAX(0,I23-N(H23)) -> 4 | K23: =IF(F23="","",J23*F23) | L23: =RANK(C23,$C$5:$C$56)+COUNTIF($C$5:C23,C23)-1 -> 19
A24: BR7HS-10 | B24: Estándar | C24: =COUNTIF(Catálogo!$E$5:$E$126,A24) -> 2 | D24: =COUNTIFS(Catálogo!$E$5:$E$126,A24,Catálogo!$I$5:$I$126,"Venta actual") -> 1 | E24: =IF(C24>=Parámetros!$B$15,"Alta",IF(C24>=Parámetros!$B$16,"Media","Baja")) -> Baja | F24: 5200 | G24: =IF(F24="","",ROUND(F24/(1-Parámetros!$B$5)/Parámetros!$B$7,0)*Parámetros!$B$7) -> 10400 | I24: =IF(E24="Alta",Parámetros!$B$19,IF(E24="Media",Parámetros!$B$20,Parámetros!$B$21)) -> 4 | J24: =MAX(0,I24-N(H24)) -> 4 | K24: =IF(F24="","",J24*F24) -> 20800 | L24: =RANK(C24,$C$5:$C$56)+COUNTIF($C$5:C24,C24)-1 -> 20
A25: BR8ES | B25: Estándar | C25: =COUNTIF(Catálogo!$E$5:$E$126,A25) -> 2 | D25: =COUNTIFS(Catálogo!$E$5:$E$126,A25,Catálogo!$I$5:$I$126,"Venta actual") -> 0 | E25: =IF(C25>=Parámetros!$B$15,"Alta",IF(C25>=Parámetros!$B$16,"Media","Baja")) -> Baja | G25: =IF(F25="","",ROUND(F25/(1-Parámetros!$B$5)/Parámetros!$B$7,0)*Parámetros!$B$7) | I25: =IF(E25="Alta",Parámetros!$B$19,IF(E25="Media",Parámetros!$B$20,Parámetros!$B$21)) -> 4 | J25: =MAX(0,I25-N(H25)) -> 4 | K25: =IF(F25="","",J25*F25) | L25: =RANK(C25,$C$5:$C$56)+COUNTIF($C$5:C25,C25)-1 -> 21
A26: BR8HS | B26: Estándar | C26: =COUNTIF(Catálogo!$E$5:$E$126,A26) -> 2 | D26: =COUNTIFS(Catálogo!$E$5:$E$126,A26,Catálogo!$I$5:$I$126,"Venta actual") -> 0 | E26: =IF(C26>=Parámetros!$B$15,"Alta",IF(C26>=Parámetros!$B$16,"Media","Baja")) -> Baja | G26: =IF(F26="","",ROUND(F26/(1-Parámetros!$B$5)/Parámetros!$B$7,0)*Parámetros!$B$7) | I26: =IF(E26="Alta",Parámetros!$B$19,IF(E26="Media",Parámetros!$B$20,Parámetros!$B$21)) -> 4 | J26: =MAX(0,I26-N(H26)) -> 4 | K26: =IF(F26="","",J26*F26) | L26: =RANK(C26,$C$5:$C$56)+COUNTIF($C$5:C26,C26)-1 -> 22
A27: CR6HSA | B27: Estándar | C27: =COUNTIF(Catálogo!$E$5:$E$126,A27) -> 2 | D27: =COUNTIFS(Catálogo!$E$5:$E$126,A27,Catálogo!$I$5:$I$126,"Venta actual") -> 1 | E27: =IF(C27>=Parámetros!$B$15,"Alta",IF(C27>=Parámetros!$B$16,"Media","Baja")) -> Baja | G27: =IF(F27="","",ROUND(F27/(1-Parámetros!$B$5)/Parámetros!$B$7,0)*Parámetros!$B$7) | I27: =IF(E27="Alta",Parámetros!$B$19,IF(E27="Media",Parámetros!$B$20,Parámetros!$B$21)) -> 4 | J27: =MAX(0,I27-N(H27)) -> 4 | K27: =IF(F27="","",J27*F27) | L27: =RANK(C27,$C$5:$C$56)+COUNTIF($C$5:C27,C27)-1 -> 23
A28: CR9EB | B28: Estándar | C28: =COUNTIF(Catálogo!$E$5:$E$126,A28) -> 2 | D28: =COUNTIFS(Catálogo!$E$5:$E$126,A28,Catálogo!$I$5:$I$126,"Venta actual") -> 0 | E28: =IF(C28>=Parámetros!$B$15,"Alta",IF(C28>=Parámetros!$B$16,"Media","Baja")) -> Baja | F28: 11500 | G28: =IF(F28="","",ROUND(F28/(1-Parámetros!$B$5)/Parámetros!$B$7,0)*Parámetros!$B$7) -> 23000 | I28: =IF(E28="Alta",Parámetros!$B$19,IF(E28="Media",Parámetros!$B$20,Parámetros!$B$21)) -> 4 | J28: =MAX(0,I28-N(H28)) -> 4 | K28: =IF(F28="","",J28*F28) -> 46000 | L28: =RANK(C28,$C$5:$C$56)+COUNTIF($C$5:C28,C28)-1 -> 24
A29: KR9E-G | B29: Estándar | C29: =COUNTIF(Catálogo!$E$5:$E$126,A29) -> 2 | D29: =COUNTIFS(Catálogo!$E$5:$E$126,A29,Catálogo!$I$5:$I$126,"Venta actual") -> 2 | E29: =IF(C29>=Parámetros!$B$15,"Alta",IF(C29>=Parámetros!$B$16,"Media","Baja")) -> Baja | G29: =IF(F29="","",ROUND(F29/(1-Parámetros!$B$5)/Parámetros!$B$7,0)*Parámetros!$B$7) | I29: =IF(E29="Alta",Parámetros!$B$19,IF(E29="Media",Parámetros!$B$20,Parámetros!$B$21)) -> 4 | J29: =MAX(0,I29-N(H29)) -> 4 | K29: =IF(F29="","",J29*F29) | L29: =RANK(C29,$C$5:$C$56)+COUNTIF($C$5:C29,C29)-1 -> 25
A30: ZFR5F | B30: Estándar | C30: =COUNTIF(Catálogo!$E$5:$E$126,A30) -> 2 | D30: =COUNTIFS(Catálogo!$E$5:$E$126,A30,Catálogo!$I$5:$I$126,"Venta actual") -> 0 | E30: =IF(C30>=Parámetros!$B$15,"Alta",IF(C30>=Parámetros!$B$16,"Media","Baja")) -> Baja | G30: =IF(F30="","",ROUND(F30/(1-Parámetros!$B$5)/Parámetros!$B$7,0)*Parámetros!$B$7) | I30: =IF(E30="Alta",Parámetros!$B$19,IF(E30="Media",Parámetros!$B$20,Parámetros!$B$21)) -> 4 | J30: =MAX(0,I30-N(H30)) -> 4 | K30: =IF(F30="","",J30*F30) | L30: =RANK(C30,$C$5:$C$56)+COUNTIF($C$5:C30,C30)-1 -> 26
A31: BPR6HS | B31: Estándar | C31: =COUNTIF(Catálogo!$E$5:$E$126,A31) -> 1 | D31: =COUNTIFS(Catálogo!$E$5:$E$126,A31,Catálogo!$I$5:$I$126,"Venta actual") -> 0 | E31: =IF(C31>=Parámetros!$B$15,"Alta",IF(C31>=Parámetros!$B$16,"Media","Baja")) -> Baja | G31: =IF(F31="","",ROUND(F31/(1-Parámetros!$B$5)/Parámetros!$B$7,0)*Parámetros!$B$7) | I31: =IF(E31="Alta",Parámetros!$B$19,IF(E31="Media",Parámetros!$B$20,Parámetros!$B$21)) -> 4 | J31: =MAX(0,I31-N(H31)) -> 4 | K31: =IF(F31="","",J31*F31) | L31: =RANK(C31,$C$5:$C$56)+COUNTIF($C$5:C31,C31)-1 -> 27
A32: BPR6HS-10 | B32: Estándar | C32: =COUNTIF(Catálogo!$E$5:$E$126,A32) -> 1 | D32: =COUNTIFS(Catálogo!$E$5:$E$126,A32,Catálogo!$I$5:$I$126,"Venta actual") -> 0 | E32: =IF(C32>=Parámetros!$B$15,"Alta",IF(C32>=Parámetros!$B$16,"Media","Baja")) -> Baja | G32: =IF(F32="","",ROUND(F32/(1-Parámetros!$B$5)/Parámetros!$B$7,0)*Parámetros!$B$7) | I32: =IF(E32="Alta",Parámetros!$B$19,IF(E32="Media",Parámetros!$B$20,Parámetros!$B$21)) -> 4 | J32: =MAX(0,I32-N(H32)) -> 4 | K32: =IF(F32="","",J32*F32) | L32: =RANK(C32,$C$5:$C$56)+COUNTIF($C$5:C32,C32)-1 -> 28
A33: BPZ8HS-10 | B33: Estándar | C33: =COUNTIF(Catálogo!$E$5:$E$126,A33) -> 1 | D33: =COUNTIFS(Catálogo!$E$5:$E$126,A33,Catálogo!$I$5:$I$126,"Venta actual") -> 0 | E33: =IF(C33>=Parámetros!$B$15,"Alta",IF(C33>=Parámetros!$B$16,"Media","Baja")) -> Baja | G33: =IF(F33="","",ROUND(F33/(1-Parámetros!$B$5)/Parámetros!$B$7,0)*Parámetros!$B$7) | I33: =IF(E33="Alta",Parámetros!$B$19,IF(E33="Media",Parámetros!$B$20,Parámetros!$B$21)) -> 4 | J33: =MAX(0,I33-N(H33)) -> 4 | K33: =IF(F33="","",J33*F33) | L33: =RANK(C33,$C$5:$C$56)+COUNTIF($C$5:C33,C33)-1 -> 29
A34: BPZ8HS-15 | B34: Estándar | C34: =COUNTIF(Catálogo!$E$5:$E$126,A34) -> 1 | D34: =COUNTIFS(Catálogo!$E$5:$E$126,A34,Catálogo!$I$5:$I$126,"Venta actual") -> 0 | E34: =IF(C34>=Parámetros!$B$15,"Alta",IF(C34>=Parámetros!$B$16,"Media","Baja")) -> Baja | G34: =IF(F34="","",ROUND(F34/(1-Parámetros!$B$5)/Parámetros!$B$7,0)*Parámetros!$B$7) | I34: =IF(E34="Alta",Parámetros!$B$19,IF(E34="Media",Parámetros!$B$20,Parámetros!$B$21)) -> 4 | J34: =MAX(0,I34-N(H34)) -> 4 | K34: =IF(F34="","",J34*F34) | L34: =RANK(C34,$C$5:$C$56)+COUNTIF($C$5:C34,C34)-1 -> 30
A35: BR5HS | B35: Estándar | C35: =COUNTIF(Catálogo!$E$5:$E$126,A35) -> 1 | D35: =COUNTIFS(Catálogo!$E$5:$E$126,A35,Catálogo!$I$5:$I$126,"Venta actual") -> 0 | E35: =IF(C35>=Parámetros!$B$15,"Alta",IF(C35>=Parámetros!$B$16,"Media","Baja")) -> Baja | G35: =IF(F35="","",ROUND(F35/(1-Parámetros!$B$5)/Parámetros!$B$7,0)*Parámetros!$B$7) | I35: =IF(E35="Alta",Parámetros!$B$19,IF(E35="Media",Parámetros!$B$20,Parámetros!$B$21)) -> 4 | J35: =MAX(0,I35-N(H35)) -> 4 | K35: =IF(F35="","",J35*F35) | L35: =RANK(C35,$C$5:$C$56)+COUNTIF($C$5:C35,C35)-1 -> 31
A36: BR7HS | B36: Estándar | C36: =COUNTIF(Catálogo!$E$5:$E$126,A36) -> 1 | D36: =COUNTIFS(Catálogo!$E$5:$E$126,A36,Catálogo!$I$5:$I$126,"Venta actual") -> 0 | E36: =IF(C36>=Parámetros!$B$15,"Alta",IF(C36>=Parámetros!$B$16,"Media","Baja")) -> Baja | G36: =IF(F36="","",ROUND(F36/(1-Parámetros!$B$5)/Parámetros!$B$7,0)*Parámetros!$B$7) | I36: =IF(E36="Alta",Parámetros!$B$19,IF(E36="Media",Parámetros!$B$20,Parámetros!$B$21)) -> 4 | J36: =MAX(0,I36-N(H36)) -> 4 | K36: =IF(F36="","",J36*F36) | L36: =RANK(C36,$C$5:$C$56)+COUNTIF($C$5:C36,C36)-1 -> 32
A37: BR8ES-11 | B37: Estándar | C37: =COUNTIF(Catálogo!$E$5:$E$126,A37) -> 1 | D37: =COUNTIFS(Catálogo!$E$5:$E$126,A37,Catálogo!$I$5:$I$126,"Venta actual") -> 0 | E37: =IF(C37>=Parámetros!$B$15,"Alta",IF(C37>=Parámetros!$B$16,"Media","Baja")) -> Baja | G37: =IF(F37="","",ROUND(F37/(1-Parámetros!$B$5)/Parámetros!$B$7,0)*Parámetros!$B$7) | I37: =IF(E37="Alta",Parámetros!$B$19,IF(E37="Media",Parámetros!$B$20,Parámetros!$B$21)) -> 4 | J37: =MAX(0,I37-N(H37)) -> 4 | K37: =IF(F37="","",J37*F37) | L37: =RANK(C37,$C$5:$C$56)+COUNTIF($C$5:C37,C37)-1 -> 33
A38: BUZ8H | B38: Estándar | C38: =COUNTIF(Catálogo!$E$5:$E$126,A38) -> 1 | D38: =COUNTIFS(Catálogo!$E$5:$E$126,A38,Catálogo!$I$5:$I$126,"Venta actual") -> 0 | E38: =IF(C38>=Parámetros!$B$15,"Alta",IF(C38>=Parámetros!$B$16,"Media","Baja")) -> Baja | G38: =IF(F38="","",ROUND(F38/(1-Parámetros!$B$5)/Parámetros!$B$7,0)*Parámetros!$B$7) | I38: =IF(E38="Alta",Parámetros!$B$19,IF(E38="Media",Parámetros!$B$20,Parámetros!$B$21)) -> 4 | J38: =MAX(0,I38-N(H38)) -> 4 | K38: =IF(F38="","",J38*F38) | L38: =RANK(C38,$C$5:$C$56)+COUNTIF($C$5:C38,C38)-1 -> 34
A39: CR6E | B39: Estándar | C39: =COUNTIF(Catálogo!$E$5:$E$126,A39) -> 1 | D39: =COUNTIFS(Catálogo!$E$5:$E$126,A39,Catálogo!$I$5:$I$126,"Venta actual") -> 0 | E39: =IF(C39>=Parámetros!$B$15,"Alta",IF(C39>=Parámetros!$B$16,"Media","Baja")) -> Baja | G39: =IF(F39="","",ROUND(F39/(1-Parámetros!$B$5)/Parámetros!$B$7,0)*Parámetros!$B$7) | I39: =IF(E39="Alta",Parámetros!$B$19,IF(E39="Media",Parámetros!$B$20,Parámetros!$B$21)) -> 4 | J39: =MAX(0,I39-N(H39)) -> 4 | K39: =IF(F39="","",J39*F39) | L39: =RANK(C39,$C$5:$C$56)+COUNTIF($C$5:C39,C39)-1 -> 35
A40: CR6HSB | B40: Estándar | C40: =COUNTIF(Catálogo!$E$5:$E$126,A40) -> 1 | D40: =COUNTIFS(Catálogo!$E$5:$E$126,A40,Catálogo!$I$5:$I$126,"Venta actual") -> 1 | E40: =IF(C40>=Parámetros!$B$15,"Alta",IF(C40>=Parámetros!$B$16,"Media","Baja")) -> Baja | G40: =IF(F40="","",ROUND(F40/(1-Parámetros!$B$5)/Parámetros!$B$7,0)*Parámetros!$B$7) | I40: =IF(E40="Alta",Parámetros!$B$19,IF(E40="Media",Parámetros!$B$20,Parámetros!$B$21)) -> 4 | J40: =MAX(0,I40-N(H40)) -> 4 | K40: =IF(F40="","",J40*F40) | L40: =RANK(C40,$C$5:$C$56)+COUNTIF($C$5:C40,C40)-1 -> 36
... A53: LFR7A | B53: Estándar | C53: =COUNTIF(Catálogo!$E$5:$E$126,A53) -> 1 | D53: =COUNTIFS(Catálogo!$E$5:$E$126,A53,Catálogo!$I$5:$I$126,"Venta actual") -> 0 | E53: =IF(C53>=Parámetros!$B$15,"Alta",IF(C53>=Parámetros!$B$16,"Media","Baja")) -> Baja | G53: =IF(F53="","",ROUND(F53/(1-Parámetros!$B$5)/Parámetros!$B$7,0)*Parámetros!$B$7) | I53: =IF(E53="Alta",Parámetros!$B$19,IF(E53="Media",Parámetros!$B$20,Parámetros!$B$21)) -> 4 | J53: =MAX(0,I53-N(H53)) -> 4 | K53: =IF(F53="","",J53*F53) | L53: =RANK(C53,$C$5:$C$56)+COUNTIF($C$5:C53,C53)-1 -> 49
A54: LKR6E-9N | B54: Estándar | C54: =COUNTIF(Catálogo!$E$5:$E$126,A54) -> 1 | D54: =COUNTIFS(Catálogo!$E$5:$E$126,A54,Catálogo!$I$5:$I$126,"Venta actual") -> 1 | E54: =IF(C54>=Parámetros!$B$15,"Alta",IF(C54>=Parámetros!$B$16,"Media","Baja")) -> Baja | F54: 9000 | G54: =IF(F54="","",ROUND(F54/(1-Parámetros!$B$5)/Parámetros!$B$7,0)*Parámetros!$B$7) -> 18000 | I54: =IF(E54="Alta",Parámetros!$B$19,IF(E54="Media",Parámetros!$B$20,Parámetros!$B$21)) -> 4 | J54: =MAX(0,I54-N(H54)) -> 4 | K54: =IF(F54="","",J54*F54) -> 36000 | L54: =RANK(C54,$C$5:$C$56)+COUNTIF($C$5:C54,C54)-1 -> 50
A55: MR6K-9 | B55: Estándar | C55: =COUNTIF(Catálogo!$E$5:$E$126,A55) -> 1 | D55: =COUNTIFS(Catálogo!$E$5:$E$126,A55,Catálogo!$I$5:$I$126,"Venta actual") -> 1 | E55: =IF(C55>=Parámetros!$B$15,"Alta",IF(C55>=Parámetros!$B$16,"Media","Baja")) -> Baja | G55: =IF(F55="","",ROUND(F55/(1-Parámetros!$B$5)/Parámetros!$B$7,0)*Parámetros!$B$7) | I55: =IF(E55="Alta",Parámetros!$B$19,IF(E55="Media",Parámetros!$B$20,Parámetros!$B$21)) -> 4 | J55: =MAX(0,I55-N(H55)) -> 4 | K55: =IF(F55="","",J55*F55) | L55: =RANK(C55,$C$5:$C$56)+COUNTIF($C$5:C55,C55)-1 -> 51
A56: ZFR4F-11 | B56: Estándar | C56: =COUNTIF(Catálogo!$E$5:$E$126,A56) -> 1 | D56: =COUNTIFS(Catálogo!$E$5:$E$126,A56,Catálogo!$I$5:$I$126,"Venta actual") -> 0 | E56: =IF(C56>=Parámetros!$B$15,"Alta",IF(C56>=Parámetros!$B$16,"Media","Baja")) -> Baja | G56: =IF(F56="","",ROUND(F56/(1-Parámetros!$B$5)/Parámetros!$B$7,0)*Parámetros!$B$7) | I56: =IF(E56="Alta",Parámetros!$B$19,IF(E56="Media",Parámetros!$B$20,Parámetros!$B$21)) -> 4 | J56: =MAX(0,I56-N(H56)) -> 4 | K56: =IF(F56="","",J56*F56) | L56: =RANK(C56,$C$5:$C$56)+COUNTIF($C$5:C56,C56)-1 -> 52
A57: Total | J57: =SUM(J5:J56) -> 304 | K57: =SUM(K5:K56) -> 628400
A59: Ejemplo: el costo de 15.000 COP para DCPR6E (celda naranja) es solo ilustrativo para mostrar cómo calcula el libro. Reemplázalo con tu costo real.
A60: Precio de lista = costo ÷ (1 − margen objetivo), redondeado. El Cotizador toma este precio automáticamente. Mientras no escribas el costo, el precio queda vacío.
A61: Stock mínimo sugerido y umbrales de prioridad salen de la hoja Parámetros (supuestos de ejemplo). 'Reponer' trata el stock vacío como cero.

Sheet Seguimiento
A1: Seguimiento de clientes y recompra
A2: Registra cada venta con el motor del cliente. El libro calcula cuándo toca el siguiente cambio de bujías y cuál es la referencia.
A4: Cliente | B4: Teléfono / WhatsApp | C4: Tipo | D4: Marca | E4: Modelo | F4: Año / serie | G4: Última venta | H4: Meses entre cambios | I4: Próxima reposición | J4: Estado | K4: Bujía NGK | L4: Bujías por motor
A5: Taller Náutico El Remo (ejemplo) | B5: 300 000 0000 (ejemplo) | C5: Taller | D5: Parsun | E5: T-40 JBMS / JBML / GBML | F5: 2024 / serie ejemplo | G5: 46127 | I5: =IF(G5="","",EDATE(G5,IF(H5="",Parámetros!$B$24,H5))) -> 46492 | J5: =IF(I5="","",IF(I5<TODAY(),"Vencida",IF(I5<=TODAY()+30,"Próximos 30 días","Al día"))) -> Al día | K5: =IF(E5="","",IFERROR(INDEX(Catálogo!$E$5:$E$126,MATCH(D5&"|"&E5,Catálogo!$M$5:$M$126,0)),"No encontrado")) -> BPR7HS | L5: =IF(E5="","",IFERROR(IF(INDEX(Catálogo!$H$5:$H$126,MATCH(D5&"|"&E5,Catálogo!$M$5:$M$126,0))="","",INDEX(Catálogo!$H$5:$H$126,MATCH(D5&"|"&E5,Catálogo!$M$5:$M$126,0))),"")) -> 2
I6: =IF(G6="","",EDATE(G6,IF(H6="",Parámetros!$B$24,H6))) | J6: =IF(I6="","",IF(I6<TODAY(),"Vencida",IF(I6<=TODAY()+30,"Próximos 30 días","Al día"))) | K6: =IF(E6="","",IFERROR(INDEX(Catálogo!$E$5:$E$126,MATCH(D6&"|"&E6,Catálogo!$M$5:$M$126,0)),"No encontrado")) | L6: =IF(E6="","",IFERROR(IF(INDEX(Catálogo!$H$5:$H$126,MATCH(D6&"|"&E6,Catálogo!$M$5:$M$126,0))="","",INDEX(Catálogo!$H$5:$H$126,MATCH(D6&"|"&E6,Catálogo!$M$5:$M$126,0))),""))
I7: =IF(G7="","",EDATE(G7,IF(H7="",Parámetros!$B$24,H7))) | J7: =IF(I7="","",IF(I7<TODAY(),"Vencida",IF(I7<=TODAY()+30,"Próximos 30 días","Al día"))) | K7: =IF(E7="","",IFERROR(INDEX(Catálogo!$E$5:$E$126,MATCH(D7&"|"&E7,Catálogo!$M$5:$M$126,0)),"No encontrado")) | L7: =IF(E7="","",IFERROR(IF(INDEX(Catálogo!$H$5:$H$126,MATCH(D7&"|"&E7,Catálogo!$M$5:$M$126,0))="","",INDEX(Catálogo!$H$5:$H$126,MATCH(D7&"|"&E7,Catálogo!$M$5:$M$126,0))),""))
I8: =IF(G8="","",EDATE(G8,IF(H8="",Parámetros!$B$24,H8))) | J8: =IF(I8="","",IF(I8<TODAY(),"Vencida",IF(I8<=TODAY()+30,"Próximos 30 días","Al día"))) | K8: =IF(E8="","",IFERROR(INDEX(Catálogo!$E$5:$E$126,MATCH(D8&"|"&E8,Catálogo!$M$5:$M$126,0)),"No encontrado")) | L8: =IF(E8="","",IFERROR(IF(INDEX(Catálogo!$H$5:$H$126,MATCH(D8&"|"&E8,Catálogo!$M$5:$M$126,0))="","",INDEX(Catálogo!$H$5:$H$126,MATCH(D8&"|"&E8,Catálogo!$M$5:$M$126,0))),""))
I9: =IF(G9="","",EDATE(G9,IF(H9="",Parámetros!$B$24,H9))) | J9: =IF(I9="","",IF(I9<TODAY(),"Vencida",IF(I9<=TODAY()+30,"Próximos 30 días","Al día"))) | K9: =IF(E9="","",IFERROR(INDEX(Catálogo!$E$5:$E$126,MATCH(D9&"|"&E9,Catálogo!$M$5:$M$126,0)),"No encontrado")) | L9: =IF(E9="","",IFERROR(IF(INDEX(Catálogo!$H$5:$H$126,MATCH(D9&"|"&E9,Catálogo!$M$5:$M$126,0))="","",INDEX(Catálogo!$H$5:$H$126,MATCH(D9&"|"&E9,Catálogo!$M$5:$M$126,0))),""))
I10: =IF(G10="","",EDATE(G10,IF(H10="",Parámetros!$B$24,H10))) | J10: =IF(I10="","",IF(I10<TODAY(),"Vencida",IF(I10<=TODAY()+30,"Próximos 30 días","Al día"))) | K10: =IF(E10="","",IFERROR(INDEX(Catálogo!$E$5:$E$126,MATCH(D10&"|"&E10,Catálogo!$M$5:$M$126,0)),"No encontrado")) | L10: =IF(E10="","",IFERROR(IF(INDEX(Catálogo!$H$5:$H$126,MATCH(D10&"|"&E10,Catálogo!$M$5:$M$126,0))="","",INDEX(Catálogo!$H$5:$H$126,MATCH(D10&"|"&E10,Catálogo!$M$5:$M$126,0))),""))
I11: =IF(G11="","",EDATE(G11,IF(H11="",Parámetros!$B$24,H11))) | J11: =IF(I11="","",IF(I11<TODAY(),"Vencida",IF(I11<=TODAY()+30,"Próximos 30 días","Al día"))) | K11: =IF(E11="","",IFERROR(INDEX(Catálogo!$E$5:$E$126,MATCH(D11&"|"&E11,Catálogo!$M$5:$M$126,0)),"No encontrado")) | L11: =IF(E11="","",IFERROR(IF(INDEX(Catálogo!$H$5:$H$126,MATCH(D11&"|"&E11,Catálogo!$M$5:$M$126,0))="","",INDEX(Catálogo!$H$5:$H$126,MATCH(D11&"|"&E11,Catálogo!$M$5:$M$126,0))),""))
I12: =IF(G12="","",EDATE(G12,IF(H12="",Parámetros!$B$24,H12))) | J12: =IF(I12="","",IF(I12<TODAY(),"Vencida",IF(I12<=TODAY()+30,"Próximos 30 días","Al día"))) | K12: =IF(E12="","",IFERROR(INDEX(Catálogo!$E$5:$E$126,MATCH(D12&"|"&E12,Catálogo!$M$5:$M$126,0)),"No encontrado")) | L12: =IF(E12="","",IFERROR(IF(INDEX(Catálogo!$H$5:$H$126,MATCH(D12&"|"&E12,Catálogo!$M$5:$M$126,0))="","",INDEX(Catálogo!$H$5:$H$126,MATCH(D12&"|"&E12,Catálogo!$M$5:$M$126,0))),""))
I13: =IF(G13="","",EDATE(G13,IF(H13="",Parámetros!$B$24,H13))) | J13: =IF(I13="","",IF(I13<TODAY(),"Vencida",IF(I13<=TODAY()+30,"Próximos 30 días","Al día"))) | K13: =IF(E13="","",IFERROR(INDEX(Catálogo!$E$5:$E$126,MATCH(D13&"|"&E13,Catálogo!$M$5:$M$126,0)),"No encontrado")) | L13: =IF(E13="","",IFERROR(IF(INDEX(Catálogo!$H$5:$H$126,MATCH(D13&"|"&E13,Catálogo!$M$5:$M$126,0))="","",INDEX(Catálogo!$H$5:$H$126,MATCH(D13&"|"&E13,Catálogo!$M$5:$M$126,0))),""))
I14: =IF(G14="","",EDATE(G14,IF(H14="",Parámetros!$B$24,H14))) | J14: =IF(I14="","",IF(I14<TODAY(),"Vencida",IF(I14<=TODAY()+30,"Próximos 30 días","Al día"))) | K14: =IF(E14="","",IFERROR(INDEX(Catálogo!$E$5:$E$126,MATCH(D14&"|"&E14,Catálogo!$M$5:$M$126,0)),"No encontrado")) | L14: =IF(E14="","",IFERROR(IF(INDEX(Catálogo!$H$5:$H$126,MATCH(D14&"|"&E14,Catálogo!$M$5:$M$126,0))="","",INDEX(Catálogo!$H$5:$H$126,MATCH(D14&"|"&E14,Catálogo!$M$5:$M$126,0))),""))
I15: =IF(G15="","",EDATE(G15,IF(H15="",Parámetros!$B$24,H15))) | J15: =IF(I15="","",IF(I15<TODAY(),"Vencida",IF(I15<=TODAY()+30,"Próximos 30 días","Al día"))) | K15: =IF(E15="","",IFERROR(INDEX(Catálogo!$E$5:$E$126,MATCH(D15&"|"&E15,Catálogo!$M$5:$M$126,0)),"No encontrado")) | L15: =IF(E15="","",IFERROR(IF(INDEX(Catálogo!$H$5:$H$126,MATCH(D15&"|"&E15,Catálogo!$M$5:$M$126,0))="","",INDEX(Catálogo!$H$5:$H$126,MATCH(D15&"|"&E15,Catálogo!$M$5:$M$126,0))),""))
I16: =IF(G16="","",EDATE(G16,IF(H16="",Parámetros!$B$24,H16))) | J16: =IF(I16="","",IF(I16<TODAY(),"Vencida",IF(I16<=TODAY()+30,"Próximos 30 días","Al día"))) | K16: =IF(E16="","",IFERROR(INDEX(Catálogo!$E$5:$E$126,MATCH(D16&"|"&E16,Catálogo!$M$5:$M$126,0)),"No encontrado")) | L16: =IF(E16="","",IFERROR(IF(INDEX(Catálogo!$H$5:$H$126,MATCH(D16&"|"&E16,Catálogo!$M$5:$M$126,0))="","",INDEX(Catálogo!$H$5:$H$126,MATCH(D16&"|"&E16,Catálogo!$M$5:$M$126,0))),""))
I17: =IF(G17="","",EDATE(G17,IF(H17="",Parámetros!$B$24,H17))) | J17: =IF(I17="","",IF(I17<TODAY(),"Vencida",IF(I17<=TODAY()+30,"Próximos 30 días","Al día"))) | K17: =IF(E17="","",IFERROR(INDEX(Catálogo!$E$5:$E$126,MATCH(D17&"|"&E17,Catálogo!$M$5:$M$126,0)),"No encontrado")) | L17: =IF(E17="","",IFERROR(IF(INDEX(Catálogo!$H$5:$H$126,MATCH(D17&"|"&E17,Catálogo!$M$5:$M$126,0))="","",INDEX(Catálogo!$H$5:$H$126,MATCH(D17&"|"&E17,Catálogo!$M$5:$M$126,0))),""))
... I34: =IF(G34="","",EDATE(G34,IF(H34="",Parámetros!$B$24,H34))) | J34: =IF(I34="","",IF(I34<TODAY(),"Vencida",IF(I34<=TODAY()+30,"Próximos 30 días","Al día"))) | K34: =IF(E34="","",IFERROR(INDEX(Catálogo!$E$5:$E$126,MATCH(D34&"|"&E34,Catálogo!$M$5:$M$126,0)),"No encontrado")) | L34: =IF(E34="","",IFERROR(IF(INDEX(Catálogo!$H$5:$H$126,MATCH(D34&"|"&E34,Catálogo!$M$5:$M$126,0))="","",INDEX(Catálogo!$H$5:$H$126,MATCH(D34&"|"&E34,Catálogo!$M$5:$M$126,0))),""))
A36: La fila 5 es un ejemplo (fecha de venta ilustrativa). Déjala de guía o sobrescríbela. 'Meses entre cambios' vacío usa el valor por defecto de Parámetros.

Sheet Parámetros
A1: Parámetros
A2: Supuestos editables que alimentan el cotizador, los precios y el stock. Todos son de ejemplo: reemplázalos con los tuyos.
A4: Precios
A5: Margen bruto objetivo sobre el precio de lista | B5: 0.5 | C5: Supuesto de ejemplo. Precio de lista = costo ÷ (1 − margen).
A6: IVA | B6: 0 | C6: Tarifa general del IVA en Colombia; confirma con tu contador si aplica a estos productos.
A7: Redondeo del precio de lista (COP) | B7: 100 | C7: El precio de lista se redondea al múltiplo más cercano de este valor.
A9: Descuento por tipo de cliente (ejemplo)
A10: Cliente final | B10: 0 | C10: Los nombres deben coincidir con la lista desplegable del Cotizador.
A11: Taller | B11: 0.1 | C11: Supuesto de ejemplo.
A12: Mayorista | B12: 0.15 | C12: Supuesto de ejemplo.
A14: Prioridad de inventario (según cuántos modelos del catálogo usa cada bujía)
A15: Prioridad Alta si la bujía la usan al menos (modelos) | B15: 5 | C15: Con los datos actuales: DCPR6E, LFR6A-11, BKR6E, DPR7EA-9, BPR7HS, LFR5A-11 y LKR6E.
A16: Prioridad Media si la usan al menos (modelos) | B16: 3 | C16: Por debajo de este número, la prioridad es Baja.
A18: Stock mínimo sugerido por prioridad (unidades)
A19: Alta | B19: 12 | C19: Supuesto de ejemplo: ajústalo a tu rotación real.
A20: Media | B20: 8 | C20: Supuesto de ejemplo.
A21: Baja | B21: 4 | C21: Supuesto de ejemplo.
A23: Seguimiento de clientes
A24: Meses entre cambios de bujía (valor por defecto) | B24: 12 | C24: Supuesto: confirma el intervalo en el manual de cada motor (se indica en horas o meses) y ajústalo por cliente en Seguimiento.
A26: Convención de colores: celdas amarillas con letra azul = se editan; letra negra = fórmula.
